Workbook

Sheet CAPITAL
A1: CAPITAL | E1: DIVISION | F1: CAPITAL/ TRADE | G1: NEW WEIGHT | H1: WEIGHT = Pers cap/ tot cap
C2: =SUM(C5:D15) -> 3350000
A5: 1 | B5: SA | C5: 150000 | E5: 30 | F5: =C5/E5 -> 5000 | G5: =F5/$F$15 -> 0.052941176 | H5: =C5/$C$2 -> 0.044776119
A6: 2 | B6: SG | C6: 700000 | E6: 35 | F6: =C6/E6 -> 20000 | G6: =F6/$F$15 -> 0.21176471 | H6: =C6/$C$2 -> 0.20895522
A7: 3 | B7: DS | C7: 2500000 | E7: 36 | F7: =C7/E7 -> 69444.444 | G7: =F7/$F$15 -> 0.73529412 | H7: =C7/$C$2 -> 0.74626866
G8: =F8/$F$15 -> 0 | H8: =C8/$C$2 -> 0
G9: =F9/$F$15 -> 0 | H9: =C9/$C$2 -> 0
G10: =F10/$F$15 -> 0 | H10: =C10/$C$2 -> 0
G11: =F11/$F$15 -> 0 | H11: =C11/$C$2 -> 0
G12: =F12/$F$15 -> 0 | H12: =C12/$C$2 -> 0
G13: =F13/$F$15 -> 0 | H13: =C13/$C$2 -> 0
G14: =F14/$F$15 -> 0 | H14: =C14/$C$2 -> 0
A15: =count(A5:A14) -> 3 | F15: =SUM(F5:F14) -> 94444.444 | G15: =SUM(G5:G14) -> 1 | H15: =SUM(H5:H14) -> 1

Sheet ENTRY
A1: Trade No. | B1: Script | C1: Entry Date | D1: Entry Price | E1: Total Qty | F1: Exit Price | G1: Exit Date | H1: SA DIVISION | I1: NK DIVISION | J1: DS DIVISION | K1: SA CAPITAL/ TRADE | L1: NK CAPITAL/ TRADE | M1: DS CAPITAL/ TRADE | N1: TOT CAPITAL/ TRADE | O1: SA WEIGHT | P1: NK WEIGHT | Q1: DS WEIGHT
A3: 1 | B3: EMULTIMQ | C3: 46023 | D3: 41.25 | E3: 2289 | F3: LIVE | H3: 30 | I3: 35 | J3: 36 | K3: =IF(H3=0,0,CAPITAL!$C$5/H3) -> 5000 | L3: =IF(I3=0,0,CAPITAL!$C$6/I3) -> 20000 | M3: =IF(J3=0,0,CAPITAL!$C$7/J3) -> 69444.444 | N3: =K3+L3+M3 -> 94444.444 | O3: =K3/N3 -> 0.052941176 | P3: =L3/N3 -> 0.21176471 | Q3: =M3/N3 -> 0.73529412
A4: 2 | B4: FMCGIETF | C4: 46024 | D4: 56.85 | E4: 1661 | F4: LIVE | H4: 20 | I4: 35 | J4: 36 | K4: =IF(H4=0,0,CAPITAL!$C$5/H4) -> 7500 | L4: =IF(I4=0,0,CAPITAL!$C$6/I4) -> 20000 | M4: =IF(J4=0,0,CAPITAL!$C$7/J4) -> 69444.444 | N4: =K4+L4+M4 -> 96944.444 | O4: =K4/N4 -> 0.077363897 | P4: =L4/N4 -> 0.20630372 | Q4: =M4/N4 -> 0.71633238
A5: 3 | B5: MOHEALTH | C5: 46027 | D5: 44.71 | E5: 2112 | F5: LIVE | H5: 50 | I5: 70 | J5: 40 | K5: =IF(H5=0,0,CAPITAL!$C$5/H5) -> 3000 | L5: =IF(I5=0,0,CAPITAL!$C$6/I5) -> 10000 | M5: =IF(J5=0,0,CAPITAL!$C$7/J5) -> 62500 | N5: =K5+L5+M5 -> 75500 | O5: =K5/N5 -> 0.039735099 | P5: =L5/N5 -> 0.13245033 | Q5: =M5/N5 -> 0.82781457
A6: 4 | B6: MOHEALTH | C6: 46029 | D6: 45.25 | E6: 2087 | F6: LIVE | H6: 30 | I6: 35 | J6: 36 | K6: =IF(H6=0,0,CAPITAL!$C$5/H6) -> 5000 | L6: =IF(I6=0,0,CAPITAL!$C$6/I6) -> 20000 | M6: =IF(J6=0,0,CAPITAL!$C$7/J6) -> 69444.444 | N6: =K6+L6+M6 -> 94444.444 | O6: =K6/N6 -> 0.052941176 | P6: =L6/N6 -> 0.21176471 | Q6: =M6/N6 -> 0.73529412
A7: 5 | B7: SILVERBEES | C7: 46030 | D7: 224.52 | E7: 840 | F7: 239.2 | G7: 46034 | H7: 30 | I7: 35 | J7: 36 | K7: =IF(H7=0,0,CAPITAL!$C$5/H7) -> 5000 | L7: =IF(I7=0,0,CAPITAL!$C$6/I7) -> 20000 | M7: =IF(J7=0,0,CAPITAL!$C$7/J7) -> 69444.444 | N7: =K7+L7+M7 -> 94444.444 | O7: =K7/N7 -> 0.052941176 | P7: =L7/N7 -> 0.21176471 | Q7: =M7/N7 -> 0.73529412
A8: 6 | B8: HNGSNGBEES | C8: 46031 | D8: 501.25 | E8: 180 | F8: 517.3 | G8: 46034 | H8: 0 | I8: 0 | J8: 36 | K8: =IF(H8=0,0,CAPITAL!$C$5/H8) -> 0 | L8: =IF(I8=0,0,CAPITAL!$C$6/I8) -> 0 | M8: =IF(J8=0,0,CAPITAL!$C$7/J8) -> 69444.444 | N8: =K8+L8+M8 -> 69444.444 | O8: =K8/N8 -> 0 | P8: =L8/N8 -> 0 | Q8: =M8/N8 -> 1
A9: 7 | B9: SILVERBEES | C9: 46036 | D9: 260.15 | E9: 269 | F9: 280.95 | G9: 46041 | H9: 0 | I9: 0 | J9: 36 | K9: =IF(H9=0,0,CAPITAL!$C$5/H9) -> 0 | L9: =IF(I9=0,0,CAPITAL!$C$6/I9) -> 0 | M9: =IF(J9=0,0,CAPITAL!$C$7/J9) -> 69444.444 | N9: =K9+L9+M9 -> 69444.444 | O9: =K9/N9 -> 0 | P9: =L9/N9 -> 0 | Q9: =M9/N9 -> 1
A10: 8 | B10: GOLDBEES | C10: 46038 | D10: 117.5 | E10: 595 | F10: 122.63 | G10: 46042 | H10: 0 | I10: 0 | J10: 36 | K10: =IF(H10=0,0,CAPITAL!$C$5/H10) -> 0 | L10: =IF(I10=0,0,CAPITAL!$C$6/I10) -> 0 | M10: =IF(J10=0,0,CAPITAL!$C$7/J10) -> 69444.444 | N10: =K10+L10+M10 -> 69444.444 | O10: =K10/N10 -> 0 | P10: =L10/N10 -> 0 | Q10: =M10/N10 -> 1
A11: 9 | B11: SILVERBEES | C11: 46038 | D11: 269.3 | E11: 259 | F11: 280.95 | G11: 46041 | H11: 0 | I11: 0 | J11: 36 | K11: =IF(H11=0,0,CAPITAL!$C$5/H11) -> 0 | L11: =IF(I11=0,0,CAPITAL!$C$6/I11) -> 0 | M11: =IF(J11=0,0,CAPITAL!$C$7/J11) -> 69444.444 | N11: =K11+L11+M11 -> 69444.444 | O11: =K11/N11 -> 0 | P11: =L11/N11 -> 0 | Q11: =M11/N11 -> 1
A12: 10 | B12: SILVER LIFE (ADITYA BIRLA) | C12: 46041 | D12: 292.94 | E12: 238 | F12: 311.85 | G12: 46042 | H12: 0 | I12: 0 | J12: 36 | K12: =IF(H12=0,0,CAPITAL!$C$5/H12) -> 0 | L12: =IF(I12=0,0,CAPITAL!$C$6/I12) -> 0 | M12: =IF(J12=0,0,CAPITAL!$C$7/J12) -> 69444.444 | N12: =K12+L12+M12 -> 69444.444 | O12: =K12/N12 -> 0 | P12: =L12/N12 -> 0 | Q12: =M12/N12 -> 1
A13: 11 | B13: TWCGOLD TEF | C13: 46042 | D13: 148.5 | E13: 473 | F13: 158.07 | G13: 46043 | H13: 0 | I13: 0 | J13: 36 | K13: =IF(H13=0,0,CAPITAL!$C$5/H13) -> 0 | L13: =IF(I13=0,0,CAPITAL!$C$6/I13) -> 0 | M13: =IF(J13=0,0,CAPITAL!$C$7/J13) -> 69444.444 | N13: =K13+L13+M13 -> 69444.444 | O13: =K13/N13 -> 0 | P13: =L13/N13 -> 0 | Q13: =M13/N13 -> 1
A14: 12 | B14: SILVERBAND (BANDHAN BANK) | C14: 46042 | D14: 326.44 | E14: 522 | F14: LIVE | H14: 0 | I14: 0 | J14: 36 | K14: =IF(H14=0,0,CAPITAL!$C$5/H14) -> 0 | L14: =IF(I14=0,0,CAPITAL!$C$6/I14) -> 0 | M14: =IF(J14=0,0,CAPITAL!$C$7/J14) -> 69444.444 | N14: =K14+L14+M14 -> 69444.444 | O14: =K14/N14 -> 0 | P14: =L14/N14 -> 0 | Q14: =M14/N14 -> 1
A15: 13 | B15: SILVERBEES | C15: 46043 | D15: 304.57 | E15: 473 | F15: 315.56 | G15: 46049 | H15: 0 | I15: 0 | J15: 36 | K15: =IF(H15=0,0,CAPITAL!$C$5/H15) -> 0 | L15: =IF(I15=0,0,CAPITAL!$C$6/I15) -> 0 | M15: =IF(J15=0,0,CAPITAL!$C$7/J15) -> 69444.444 | N15: =K15+L15+M15 -> 69444.444 | O15: =K15/N15 -> 0 | P15: =L15/N15 -> 0 | Q15: =M15/N15 -> 1
A16: 14 | B16: SILVERBAND (BANDHAN BANK) | C16: 46044 | D16: 295.2 | E16: 237 | F16: LIVE | H16: 0 | I16: 0 | J16: 36 | K16: =IF(H16=0,0,CAPITAL!$C$5/H16) -> 0 | L16: =IF(I16=0,0,CAPITAL!$C$6/I16) -> 0 | M16: =IF(J16=0,0,CAPITAL!$C$7/J16) -> 69444.444 | N16: =K16+L16+M16 -> 69444.444 | O16: =K16/N16 -> 0 | P16: =L16/N16 -> 0 | Q16: =M16/N16 -> 1
A17: 15 | B17: SILVERBEES | C17: 46044 | D17: 271.82 | E17: 257 | F17: 315.56 | G17: 46049 | H17: 0 | I17: 0 | J17: 36 | K17: =IF(H17=0,0,CAPITAL!$C$5/H17) -> 0 | L17: =IF(I17=0,0,CAPITAL!$C$6/I17) -> 0 | M17: =IF(J17=0,0,CAPITAL!$C$7/J17) -> 69444.444 | N17: =K17+L17+M17 -> 69444.444 | O17: =K17/N17 -> 0 | P17: =L17/N17 -> 0 | Q17: =M17/N17 -> 1
A18: 16 | B18: SILVERBEES | H18: 0 | I18: 0 | J18: 36 | K18: =IF(H18=0,0,CAPITAL!$C$5/H18) -> 0 | L18: =IF(I18=0,0,CAPITAL!$C$6/I18) -> 0 | M18: =IF(J18=0,0,CAPITAL!$C$7/J18) -> 69444.444 | N18: =K18+L18+M18 -> 69444.444 | O18: =K18/N18 -> 0 | P18: =L18/N18 -> 0 | Q18: =M18/N18 -> 1
A19: 17 | B19: SILVERBEES | H19: 0 | I19: 0 | J19: 36 | K19: =IF(H19=0,0,CAPITAL!$C$5/H19) -> 0 | L19: =IF(I19=0,0,CAPITAL!$C$6/I19) -> 0 | M19: =IF(J19=0,0,CAPITAL!$C$7/J19) -> 69444.444 | N19: =K19+L19+M19 -> 69444.444 | O19: =K19/N19 -> 0 | P19: =L19/N19 -> 0 | Q19: =M19/N19 -> 1
A20: 18 | B20: SILVERBEES | H20: 0 | I20: 35 | J20: 36 | K20: =IF(H20=0,0,CAPITAL!$C$5/H20) -> 0 | L20: =IF(I20=0,0,CAPITAL!$C$6/I20) -> 20000 | M20: =IF(J20=0,0,CAPITAL!$C$7/J20) -> 69444.444 | N20: =K20+L20+M20 -> 89444.444 | O20: =K20/N20 -> 0 | P20: =L20/N20 -> 0.22360248 | Q20: =M20/N20 -> 0.77639752
A21: 19 | B21: SILVERBEES | H21: 30 | I21: 35 | J21: 36 | K21: =IF(H21=0,0,CAPITAL!$C$5/H21) -> 5000 | L21: =IF(I21=0,0,CAPITAL!$C$6/I21) -> 20000 | M21: =IF(J21=0,0,CAPITAL!$C$7/J21) -> 69444.444 | N21: =K21+L21+M21 -> 94444.444 | O21: =K21/N21 -> 0.052941176 | P21: =L21/N21 -> 0.21176471 | Q21: =M21/N21 -> 0.73529412
A22: 20 | B22: SILVERBEES | H22: 30 | I22: 35 | J22: 36 | K22: =IF(H22=0,0,CAPITAL!$C$5/H22) -> 5000 | L22: =IF(I22=0,0,CAPITAL!$C$6/I22) -> 20000 | M22: =IF(J22=0,0,CAPITAL!$C$7/J22) -> 69444.444 | N22: =K22+L22+M22 -> 94444.444 | O22: =K22/N22 -> 0.052941176 | P22: =L22/N22 -> 0.21176471 | Q22: =M22/N22 -> 0.73529412
A23: 21 | B23: SILVERBEES | H23: 30 | I23: 35 | J23: 36 | K23: =IF(H23=0,0,CAPITAL!$C$5/H23) -> 5000 | L23: =IF(I23=0,0,CAPITAL!$C$6/I23) -> 20000 | M23: =IF(J23=0,0,CAPITAL!$C$7/J23) -> 69444.444 | N23: =K23+L23+M23 -> 94444.444 | O23: =K23/N23 -> 0.052941176 | P23: =L23/N23 -> 0.21176471 | Q23: =M23/N23 -> 0.73529412
A24: 22 | B24: SILVERBEES | H24: 30 | I24: 35 | J24: 36 | K24: =IF(H24=0,0,CAPITAL!$C$5/H24) -> 5000 | L24: =IF(I24=0,0,CAPITAL!$C$6/I24) -> 20000 | M24: =IF(J24=0,0,CAPITAL!$C$7/J24) -> 69444.444 | N24: =K24+L24+M24 -> 94444.444 | O24: =K24/N24 -> 0.052941176 | P24: =L24/N24 -> 0.21176471 | Q24: =M24/N24 -> 0.73529412
A25: 23 | B25: SILVERBEES | H25: 30 | I25: 35 | J25: 36 | K25: =IF(H25=0,0,CAPITAL!$C$5/H25) -> 5000 | L25: =IF(I25=0,0,CAPITAL!$C$6/I25) -> 20000 | M25: =IF(J25=0,0,CAPITAL!$C$7/J25) -> 69444.444 | N25: =K25+L25+M25 -> 94444.444 | O25: =K25/N25 -> 0.052941176 | P25: =L25/N25 -> 0.21176471 | Q25: =M25/N25 -> 0.73529412
A26: 24 | B26: SILVERBEES | H26: 30 | I26: 35 | J26: 36 | K26: =IF(H26=0,0,CAPITAL!$C$5/H26) -> 5000 | L26: =IF(I26=0,0,CAPITAL!$C$6/I26) -> 20000 | M26: =IF(J26=0,0,CAPITAL!$C$7/J26) -> 69444.444 | N26: =K26+L26+M26 -> 94444.444 | O26: =K26/N26 -> 0.052941176 | P26: =L26/N26 -> 0.21176471 | Q26: =M26/N26 -> 0.73529412
A27: 25 | B27: SILVERBEES | H27: 30 | I27: 35 | J27: 36 | K27: =IF(H27=0,0,CAPITAL!$C$5/H27) -> 5000 | L27: =IF(I27=0,0,CAPITAL!$C$6/I27) -> 20000 | M27: =IF(J27=0,0,CAPITAL!$C$7/J27) -> 69444.444 | N27: =K27+L27+M27 -> 94444.444 | O27: =K27/N27 -> 0.052941176 | P27: =L27/N27 -> 0.21176471 | Q27: =M27/N27 -> 0.73529412
A28: 26 | B28: SILVERBEES | H28: 30 | I28: 35 | J28: 36 | K28: =IF(H28=0,0,CAPITAL!$C$5/H28) -> 5000 | L28: =IF(I28=0,0,CAPITAL!$C$6/I28) -> 20000 | M28: =IF(J28=0,0,CAPITAL!$C$7/J28) -> 69444.444 | N28: =K28+L28+M28 -> 94444.444 | O28: =K28/N28 -> 0.052941176 | P28: =L28/N28 -> 0.21176471 | Q28: =M28/N28 -> 0.73529412
A29: 27 | B29: SILVERBEES | H29: 30 | I29: 35 | J29: 36 | K29: =IF(H29=0,0,CAPITAL!$C$5/H29) -> 5000 | L29: =IF(I29=0,0,CAPITAL!$C$6/I29) -> 20000 | M29: =IF(J29=0,0,CAPITAL!$C$7/J29) -> 69444.444 | N29: =K29+L29+M29 -> 94444.444 | O29: =K29/N29 -> 0.052941176 | P29: =L29/N29 -> 0.21176471 | Q29: =M29/N29 -> 0.73529412
... A494: 492 | B494: SILVERBEES | H494: 30 | I494: 35 | J494: 36 | K494: =IF(H494=0,0,CAPITAL!$C$5/H494) -> 5000 | L494: =IF(I494=0,0,CAPITAL!$C$6/I494) -> 20000 | M494: =IF(J494=0,0,CAPITAL!$C$7/J494) -> 69444.444 | N494: =K494+L494+M494 -> 94444.444 | O494: =K494/N494 -> 0.052941176 | P494: =L494/N494 -> 0.21176471 | Q494: =M494/N494 -> 0.73529412
A495: 493 | H495: 30 | I495: 35 | J495: 36 | K495: =IF(H495=0,0,CAPITAL!$C$5/H495) -> 5000 | L495: =IF(I495=0,0,CAPITAL!$C$6/I495) -> 20000 | M495: =IF(J495=0,0,CAPITAL!$C$7/J495) -> 69444.444 | N495: =K495+L495+M495 -> 94444.444 | O495: =K495/N495 -> 0.052941176 | P495: =L495/N495 -> 0.21176471 | Q495: =M495/N495 -> 0.73529412
A496: 494 | H496: 30 | I496: 35 | J496: 36 | K496: =IF(H496=0,0,CAPITAL!$C$5/H496) -> 5000 | L496: =IF(I496=0,0,CAPITAL!$C$6/I496) -> 20000 | M496: =IF(J496=0,0,CAPITAL!$C$7/J496) -> 69444.444 | N496: =K496+L496+M496 -> 94444.444 | O496: =K496/N496 -> 0.052941176 | P496: =L496/N496 -> 0.21176471 | Q496: =M496/N496 -> 0.73529412
A497: 495 | H497: 30 | I497: 35 | J497: 36 | K497: =IF(H497=0,0,CAPITAL!$C$5/H497) -> 5000 | L497: =IF(I497=0,0,CAPITAL!$C$6/I497) -> 20000 | M497: =IF(J497=0,0,CAPITAL!$C$7/J497) -> 69444.444 | N497: =K497+L497+M497 -> 94444.444 | O497: =K497/N497 -> 0.052941176 | P497: =L497/N497 -> 0.21176471 | Q497: =M497/N497 -> 0.73529412
A498: 496 | H498: 30 | I498: 35 | J498: 36 | K498: =IF(H498=0,0,CAPITAL!$C$5/H498) -> 5000 | L498: =IF(I498=0,0,CAPITAL!$C$6/I498) -> 20000 | M498: =IF(J498=0,0,CAPITAL!$C$7/J498) -> 69444.444 | N498: =K498+L498+M498 -> 94444.444 | O498: =K498/N498 -> 0.052941176 | P498: =L498/N498 -> 0.21176471 | Q498: =M498/N498 -> 0.73529412
A499: 497 | H499: 30 | I499: 35 | J499: 36 | K499: =IF(H499=0,0,CAPITAL!$C$5/H499) -> 5000 | L499: =IF(I499=0,0,CAPITAL!$C$6/I499) -> 20000 | M499: =IF(J499=0,0,CAPITAL!$C$7/J499) -> 69444.444 | N499: =K499+L499+M499 -> 94444.444 | O499: =K499/N499 -> 0.052941176 | P499: =L499/N499 -> 0.21176471 | Q499: =M499/N499 -> 0.73529412
A500: 498 | H500: 30 | I500: 35 | J500: 36 | K500: =IF(H500=0,0,CAPITAL!$C$5/H500) -> 5000 | L500: =IF(I500=0,0,CAPITAL!$C$6/I500) -> 20000 | M500: =IF(J500=0,0,CAPITAL!$C$7/J500) -> 69444.444 | N500: =K500+L500+M500 -> 94444.444 | O500: =K500/N500 -> 0.052941176 | P500: =L500/N500 -> 0.21176471 | Q500: =M500/N500 -> 0.73529412
A501: 499 | H501: 30 | I501: 35 | J501: 36 | K501: =IF(H501=0,0,CAPITAL!$C$5/H501) -> 5000 | L501: =IF(I501=0,0,CAPITAL!$C$6/I501) -> 20000 | M501: =IF(J501=0,0,CAPITAL!$C$7/J501) -> 69444.444 | N501: =K501+L501+M501 -> 94444.444 | O501: =K501/N501 -> 0.052941176 | P501: =L501/N501 -> 0.21176471 | Q501: =M501/N501 -> 0.73529412
A502: 500 | H502: 30 | I502: 35 | J502: 36 | K502: =IF(H502=0,0,CAPITAL!$C$5/H502) -> 5000 | L502: =IF(I502=0,0,CAPITAL!$C$6/I502) -> 20000 | M502: =IF(J502=0,0,CAPITAL!$C$7/J502) -> 69444.444 | N502: =K502+L502+M502 -> 94444.444 | O502: =K502/N502 -> 0.052941176 | P502: =L502/N502 -> 0.21176471 | Q502: =M502/N502 -> 0.73529412
H503: 30 | I503: 35 | J503: 36 | K503: =IF(H503=0,0,CAPITAL!$C$5/H503) -> 5000 | L503: =IF(I503=0,0,CAPITAL!$C$6/I503) -> 20000 | M503: =IF(J503=0,0,CAPITAL!$C$7/J503) -> 69444.444 | N503: =K503+L503+M503 -> 94444.444 | O503: =K503/N503 -> 0.052941176 | P503: =L503/N503 -> 0.21176471 | Q503: =M503/N503 -> 0.73529412
H504: 30 | I504: 35 | J504: 36 | K504: =IF(H504=0,0,CAPITAL!$C$5/H504) -> 5000 | L504: =IF(I504=0,0,CAPITAL!$C$6/I504) -> 20000 | M504: =IF(J504=0,0,CAPITAL!$C$7/J504) -> 69444.444 | N504: =K504+L504+M504 -> 94444.444 | O504: =K504/N504 -> 0.052941176 | P504: =L504/N504 -> 0.21176471 | Q504: =M504/N504 -> 0.73529412
H505: 30 | I505: 35 | J505: 36 | K505: =IF(H505=0,0,CAPITAL!$C$5/H505) -> 5000 | L505: =IF(I505=0,0,CAPITAL!$C$6/I505) -> 20000 | M505: =IF(J505=0,0,CAPITAL!$C$7/J505) -> 69444.444 | N505: =K505+L505+M505 -> 94444.444 | O505: =K505/N505 -> 0.052941176 | P505: =L505/N505 -> 0.21176471 | Q505: =M505/N505 -> 0.73529412
H506: 30 | I506: 35 | J506: 36 | K506: =IF(H506=0,0,CAPITAL!$C$5/H506) -> 5000 | L506: =IF(I506=0,0,CAPITAL!$C$6/I506) -> 20000 | M506: =IF(J506=0,0,CAPITAL!$C$7/J506) -> 69444.444 | N506: =K506+L506+M506 -> 94444.444 | O506: =K506/N506 -> 0.052941176 | P506: =L506/N506 -> 0.21176471 | Q506: =M506/N506 -> 0.73529412
H507: 30 | I507: 35 | J507: 36 | K507: =IF(H507=0,0,CAPITAL!$C$5/H507) -> 5000 | L507: =IF(I507=0,0,CAPITAL!$C$6/I507) -> 20000 | M507: =IF(J507=0,0,CAPITAL!$C$7/J507) -> 69444.444 | N507: =K507+L507+M507 -> 94444.444 | O507: =K507/N507 -> 0.052941176 | P507: =L507/N507 -> 0.21176471 | Q507: =M507/N507 -> 0.73529412
H508: 30 | I508: 35 | J508: 36 | K508: =IF(H508=0,0,CAPITAL!$C$5/H508) -> 5000 | L508: =IF(I508=0,0,CAPITAL!$C$6/I508) -> 20000 | M508: =IF(J508=0,0,CAPITAL!$C$7/J508) -> 69444.444 | N508: =K508+L508+M508 -> 94444.444 | O508: =K508/N508 -> 0.052941176 | P508: =L508/N508 -> 0.21176471 | Q508: =M508/N508 -> 0.73529412
H509: 30 | I509: 35 | J509: 36 | K509: =IF(H509=0,0,CAPITAL!$C$5/H509) -> 5000 | L509: =IF(I509=0,0,CAPITAL!$C$6/I509) -> 20000 | M509: =IF(J509=0,0,CAPITAL!$C$7/J509) -> 69444.444 | N509: =K509+L509+M509 -> 94444.444 | O509: =K509/N509 -> 0.052941176 | P509: =L509/N509 -> 0.21176471 | Q509: =M509/N509 -> 0.73529412
H510: 30 | I510: 35 | J510: 36 | K510: =IF(H510=0,0,CAPITAL!$C$5/H510) -> 5000 | L510: =IF(I510=0,0,CAPITAL!$C$6/I510) -> 20000 | M510: =IF(J510=0,0,CAPITAL!$C$7/J510) -> 69444.444 | N510: =K510+L510+M510 -> 94444.444 | O510: =K510/N510 -> 0.052941176 | P510: =L510/N510 -> 0.21176471 | Q510: =M510/N510 -> 0.73529412
H511: 30 | I511: 35 | J511: 36 | K511: =IF(H511=0,0,CAPITAL!$C$5/H511) -> 5000 | L511: =IF(I511=0,0,CAPITAL!$C$6/I511) -> 20000 | M511: =IF(J511=0,0,CAPITAL!$C$7/J511) -> 69444.444 | N511: =K511+L511+M511 -> 94444.444 | O511: =K511/N511 -> 0.052941176 | P511: =L511/N511 -> 0.21176471 | Q511: =M511/N511 -> 0.73529412
H512: 30 | I512: 35 | J512: 36 | K512: =IF(H512=0,0,CAPITAL!$C$5/H512) -> 5000 | L512: =IF(I512=0,0,CAPITAL!$C$6/I512) -> 20000 | M512: =IF(J512=0,0,CAPITAL!$C$7/J512) -> 69444.444 | N512: =K512+L512+M512 -> 94444.444 | O512: =K512/N512 -> 0.052941176 | P512: =L512/N512 -> 0.21176471 | Q512: =M512/N512 -> 0.73529412
H513: 30 | I513: 35 | J513: 36 | K513: =IF(H513=0,0,CAPITAL!$C$5/H513) -> 5000 | L513: =IF(I513=0,0,CAPITAL!$C$6/I513) -> 20000 | M513: =IF(J513=0,0,CAPITAL!$C$7/J513) -> 69444.444 | N513: =K513+L513+M513 -> 94444.444 | O513: =K513/N513 -> 0.052941176 | P513: =L513/N513 -> 0.21176471 | Q513: =M513/N513 -> 0.73529412
H514: 30 | I514: 35 | J514: 36 | K514: =IF(H514=0,0,CAPITAL!$C$5/H514) -> 5000 | L514: =IF(I514=0,0,CAPITAL!$C$6/I514) -> 20000 | M514: =IF(J514=0,0,CAPITAL!$C$7/J514) -> 69444.444 | N514: =K514+L514+M514 -> 94444.444 | O514: =K514/N514 -> 0.052941176 | P514: =L514/N514 -> 0.21176471 | Q514: =M514/N514 -> 0.73529412
... H1000: 30 | I1000: 35 | J1000: 36 | K1000: =IF(H1000=0,0,CAPITAL!$C$5/H1000) -> 5000 | L1000: =IF(I1000=0,0,CAPITAL!$C$6/I1000) -> 20000 | M1000: =IF(J1000=0,0,CAPITAL!$C$7/J1000) -> 69444.444 | N1000: =K1000+L1000+M1000 -> 94444.444 | O1000: =K1000/N1000 -> 0.052941176 | P1000: =L1000/N1000 -> 0.21176471 | Q1000: =M1000/N1000 -> 0.73529412

Sheet JOURNAL
B1: m
M2: 2026
C3: Total Gain on Capital → | K3: =IFERROR(__xludf.DUMMYFUNCTION("SUM( FILTER(X9:X1015, ISNUMBER(X9:X1015)) )"),0.015051871641791037) -> 0.015051872 | L3: =IFERROR(__xludf.DUMMYFUNCTION("SUM( FILTER(S9:S1015, ISNUMBER(S9:S1015)) )"),50423.769999999975) -> 50423.77
U5: TOTAL CAPITAL | X5: =CAPITAL!C2 -> 3350000
B6: Trade No. | C6: Script | D6: Capital | E6: Entry Date | F6: Entry Price | G6: Total Qty | H6: SA - Qty | I6: SG - Qty | J6: DS - Qty | K6: Investment | L6: Exit Price | M6: Exit Date | N6: ROI | T6: =IFERROR(__xludf.DUMMYFUNCTION("SUM( FILTER(T9:T1015, ISNUMBER(T9:T1015)) )"),633.4594293239675) -> 633.45943 | U6: =IFERROR(__xludf.DUMMYFUNCTION("SUM( FILTER(U9:U1015, ISNUMBER(U9:U1015)) )"),2520.9251799824374) -> 2520.9252 | V6: =IFERROR(__xludf.DUMMYFUNCTION("SUM( FILTER(V9:V1015, ISNUMBER(V9:V1015)) )"),47648.81524143984) -> 47648.815 | X6: ROC | Y6: Brokerage | Z6: Brokerage - SA | AA6: Brokerage - SG | AB6: Brokerage - DS
N7: % | O7: Profit | P7: SA Profit | Q7: SG Profit | R7: DS Profit | S7: Net Profit | T7: SA Net Profit | U7: SG Net Profit | V7: DS Net Profit | W7: Net % | X7: %
A9: MOM30IETF | B9: 1 | C9: =ENTRY!B3 -> EMULTIMQ | D9: =CAPITAL!$C$2 -> 3350000 | E9: =ENTRY!C3 -> 46023 | F9: =ENTRY!D3 -> 41.25 | G9: =ENTRY!E3 -> 2289 | H9: =G9*ENTRY!$O3 -> 121.18235 | I9: =G9*ENTRY!$P3 -> 484.72941 | J9: =G9*ENTRY!$Q3 -> 1683.0882 | K9: =F9*G9 -> 94421.25 | L9: =ENTRY!F3 -> LIVE | M9: =ENTRY!G3 | N9: =IFERROR(((L9-F9)*G9)/K9,"") | O9: =IFERROR(N9*K9,"") -> 0 | P9: =IFERROR((F9*H9)*N9,"") -> 0 | Q9: =IFERROR((F9*I9)*N9,"") -> 0 | R9: =IFERROR((F9*J9)*N9,"") -> 0 | S9: =IFERROR(O9-Y9,"") | T9: =IFERROR(P9-Z9,"") | U9: =IFERROR(Q9-AA9,"") | V9: =IFERROR(R9-AB9,"") | W9: =IFERROR(S9/K9,"") -> 0 | X9: =IFERROR(S9/D9,"") -> 0 | Y9: =Brokerage(F9, L9, G9) -> ERR | Z9: =IF(H9=0,0,CAPITAL!$H$5*Y9) -> #VALUE! | AA9: =IF(I9=0,0,CAPITAL!$H$6*Y9) -> #VALUE! | AB9: =IF(J9=0,0,CAPITAL!$H$7*Y9) -> #VALUE!
A10: NIFTYQLITY | B10: 2 | C10: =ENTRY!B4 -> FMCGIETF | D10: =CAPITAL!$C$2 -> 3350000 | E10: =ENTRY!C4 -> 46024 | F10: =ENTRY!D4 -> 56.85 | G10: =ENTRY!E4 -> 1661 | H10: =G10*ENTRY!$O4 -> 128.50143 | I10: =G10*ENTRY!$P4 -> 342.67049 | J10: =G10*ENTRY!$Q4 -> 1189.8281 | K10: =F10*G10 -> 94427.85 | L10: =ENTRY!F4 -> LIVE | M10: =ENTRY!G4 | N10: =IFERROR(((L10-F10)*G10)/K10,"") | O10: =IFERROR(N10*K10,"") -> 0 | P10: =IFERROR((F10*H10)*N10,"") -> 0 | Q10: =IFERROR((F10*I10)*N10,"") -> 0 | R10: =IFERROR((F10*J10)*N10,"") -> 0 | S10: =IFERROR(O10-Y10,"") | T10: =IFERROR(P10-Z10,"") | U10: =IFERROR(Q10-AA10,"") | V10: =IFERROR(R10-AB10,"") | W10: =IFERROR(S10/K10,"") -> 0 | X10: =S10/D10 -> 0 | Y10: =Brokerage(F10, L10, G10) -> ERR | Z10: =IF(H10=0,0,CAPITAL!$H$5*Y10) -> #VALUE! | AA10: =IF(I10=0,0,CAPITAL!$H$6*Y10) -> #VALUE! | AB10: =IF(J10=0,0,CAPITAL!$H$7*Y10) -> #VALUE!
A11: VAL30IETF | B11: 3 | C11: =ENTRY!B5 -> MOHEALTH | D11: =CAPITAL!$C$2 -> 3350000 | E11: =ENTRY!C5 -> 46027 | F11: =ENTRY!D5 -> 44.71 | G11: =ENTRY!E5 -> 2112 | H11: =G11*ENTRY!$O5 -> 83.92053 | I11: =G11*ENTRY!$P5 -> 279.7351 | J11: =G11*ENTRY!$Q5 -> 1748.3444 | K11: =F11*G11 -> 94427.52 | L11: =ENTRY!F5 -> LIVE | M11: =ENTRY!G5 | N11: =IFERROR(((L11-F11)*G11)/K11,"") | O11: =IFERROR(N11*K11,"") -> 0 | P11: =IFERROR((F11*H11)*N11,"") -> 0 | Q11: =IFERROR((F11*I11)*N11,"") -> 0 | R11: =IFERROR((F11*J11)*N11,"") -> 0 | S11: =IFERROR(O11-Y11,"") | T11: =IFERROR(P11-Z11,"") | U11: =IFERROR(Q11-AA11,"") | V11: =IFERROR(R11-AB11,"") | W11: =IFERROR(S11/K11,"") -> 0 | X11: =IFERROR(S11/D11,"") -> 0 | Y11: =Brokerage(F11, L11, G11) -> ERR | Z11: =IF(H11=0,0,CAPITAL!$H$5*Y11) -> #VALUE! | AA11: =IF(I11=0,0,CAPITAL!$H$6*Y11) -> #VALUE! | AB11: =IF(J11=0,0,CAPITAL!$H$7*Y11) -> #VALUE!
A12: ABSLPSE | B12: 4 | C12: =ENTRY!B6 -> MOHEALTH | D12: =CAPITAL!$C$2 -> 3350000 | E12: =ENTRY!C6 -> 46029 | F12: =ENTRY!D6 -> 45.25 | G12: =ENTRY!E6 -> 2087 | H12: =G12*ENTRY!$O6 -> 110.48824 | I12: =G12*ENTRY!$P6 -> 441.95294 | J12: =G12*ENTRY!$Q6 -> 1534.5588 | K12: =F12*G12 -> 94436.75 | L12: =ENTRY!F6 -> LIVE | M12: =ENTRY!G6 | N12: =IFERROR(((L12-F12)*G12)/K12,"") | O12: =IFERROR(N12*K12,"") -> 0 | P12: =IFERROR((F12*H12)*N12,"") -> 0 | Q12: =IFERROR((F12*I12)*N12,"") -> 0 | R12: =IFERROR((F12*J12)*N12,"") -> 0 | S12: =IFERROR(O12-Y12,"") | T12: =IFERROR(P12-Z12,"") | U12: =IFERROR(Q12-AA12,"") | V12: =IFERROR(R12-AB12,"") | W12: =IFERROR(S12/K12,"") -> 0 | X12: =S12/D12 -> 0 | Y12: =Brokerage(F12, L12, G12) -> ERR | Z12: =IF(H12=0,0,CAPITAL!$H$5*Y12) -> #VALUE! | AA12: =IF(I12=0,0,CAPITAL!$H$6*Y12) -> #VALUE! | AB12: =IF(J12=0,0,CAPITAL!$H$7*Y12) -> #VALUE!
A13: UTISXN50 | B13: 5 | C13: =ENTRY!B7 -> SILVERBEES | D13: =CAPITAL!$C$2 -> 3350000 | E13: =ENTRY!C7 -> 46030 | F13: =ENTRY!D7 -> 224.52 | G13: =ENTRY!E7 -> 840 | H13: =G13*ENTRY!$O7 -> 44.470588 | I13: =G13*ENTRY!$P7 -> 177.88235 | J13: =G13*ENTRY!$Q7 -> 617.64706 | K13: =F13*G13 -> 188596.8 | L13: =ENTRY!F7 -> 239.2 | M13: =ENTRY!G7 -> 46034 | N13: =IFERROR(((L13-F13)*G13)/K13,"") -> 0.06538393 | O13: =IFERROR(N13*K13,"") -> 12331.2 | P13: =IFERROR((F13*H13)*N13,"") -> 652.82824 | Q13: =IFERROR((F13*I13)*N13,"") -> 2611.3129 | R13: =IFERROR((F13*J13)*N13,"") -> 9067.0588 | S13: =IFERROR(O13-Y13,"") -> 11898.63 | T13: =IFERROR(P13-Z13,"") -> 633.45943 | U13: =IFERROR(Q13-AA13,"") -> 2520.9252 | V13: =IFERROR(R13-AB13,"") -> 8744.2454 | W13: =IFERROR(S13/K13,"") -> 0.063090307 | X13: =IFERROR(S13/D13,"") -> 0.0035518299 | Y13: =Brokerage(F13, L13, G13) -> 432.57 | Z13: =IF(H13=0,0,CAPITAL!$H$5*Y13) -> 19.368806 | AA13: =IF(I13=0,0,CAPITAL!$H$6*Y13) -> 90.387761 | AB13: =IF(J13=0,0,CAPITAL!$H$7*Y13) -> 322.81343
A14: CPSEETF | B14: 6 | C14: =ENTRY!B8 -> HNGSNGBEES | D14: =CAPITAL!$C$2 -> 3350000 | E14: =ENTRY!C8 -> 46031 | F14: =ENTRY!D8 -> 501.25 | G14: =ENTRY!E8 -> 180 | H14: =G14*ENTRY!$O8 -> 0 | I14: =G14*ENTRY!$P8 -> 0 | J14: =G14*ENTRY!$Q8 -> 180 | K14: =F14*G14 -> 90225 | L14: =ENTRY!F8 -> 517.3 | M14: =ENTRY!G8 -> 46034 | N14: =IFERROR(((L14-F14)*G14)/K14,"") -> 0.03201995 | O14: =IFERROR(N14*K14,"") -> 2889 | P14: =IFERROR((F14*H14)*N14,"") -> 0 | Q14: =IFERROR((F14*I14)*N14,"") -> 0 | R14: =IFERROR((F14*J14)*N14,"") -> 2889 | S14: =IFERROR(O14-Y14,"") -> 2685.14 | T14: =IFERROR(P14-Z14,"") -> 0 | U14: =IFERROR(Q14-AA14,"") -> 0 | V14: =IFERROR(R14-AB14,"") -> 2736.8657 | W14: =IFERROR(S14/K14,"") -> 0.029760488 | X14: =S14/D14 -> 0.00080153433 | Y14: =Brokerage(F14, L14, G14) -> 203.86 | Z14: =IF(H14=0,0,CAPITAL!$H$5*Y14) -> 0 | AA14: =IF(I14=0,0,CAPITAL!$H$6*Y14) -> 0 | AB14: =IF(J14=0,0,CAPITAL!$H$7*Y14) -> 152.13433
A15: GOLDBEES | B15: 7 | C15: =ENTRY!B9 -> SILVERBEES | D15: =CAPITAL!$C$2 -> 3350000 | E15: =ENTRY!C9 -> 46036 | F15: =ENTRY!D9 -> 260.15 | G15: =ENTRY!E9 -> 269 | H15: =G15*ENTRY!$O9 -> 0 | I15: =G15*ENTRY!$P9 -> 0 | J15: =G15*ENTRY!$Q9 -> 269 | K15: =F15*G15 -> 69980.35 | L15: =ENTRY!F9 -> 280.95 | M15: =ENTRY!G9 -> 46041 | N15: =IFERROR(((L15-F15)*G15)/K15,"") -> 0.079953873 | O15: =IFERROR(N15*K15,"") -> 5595.2 | P15: =IFERROR((F15*H15)*N15,"") -> 0 | Q15: =IFERROR((F15*I15)*N15,"") -> 0 | R15: =IFERROR((F15*J15)*N15,"") -> 5595.2 | S15: =IFERROR(O15-Y15,"") -> 5433.75 | T15: =IFERROR(P15-Z15,"") -> 0 | U15: =IFERROR(Q15-AA15,"") -> 0 | V15: =IFERROR(R15-AB15,"") -> 5474.7149 | W15: =IFERROR(S15/K15,"") -> 0.077646797 | X15: =IFERROR(S15/D15,"") -> 0.0016220149 | Y15: =Brokerage(F15, L15, G15) -> 161.45 | Z15: =IF(H15=0,0,CAPITAL!$H$5*Y15) -> 0 | AA15: =IF(I15=0,0,CAPITAL!$H$6*Y15) -> 0 | AB15: =IF(J15=0,0,CAPITAL!$H$7*Y15) -> 120.48507
A16: HNGSNGBEES | B16: 8 | C16: =ENTRY!B10 -> GOLDBEES | D16: =CAPITAL!$C$2 -> 3350000 | E16: =ENTRY!C10 -> 46038 | F16: =ENTRY!D10 -> 117.5 | G16: =ENTRY!E10 -> 595 | H16: =G16*ENTRY!$O10 -> 0 | I16: =G16*ENTRY!$P10 -> 0 | J16: =G16*ENTRY!$Q10 -> 595 | K16: =F16*G16 -> 69912.5 | L16: =ENTRY!F10 -> 122.63 | M16: =ENTRY!G10 -> 46042 | N16: =IFERROR(((L16-F16)*G16)/K16,"") -> 0.043659574 | O16: =IFERROR(N16*K16,"") -> 3052.35 | P16: =IFERROR((F16*H16)*N16,"") -> 0 | Q16: =IFERROR((F16*I16)*N16,"") -> 0 | R16: =IFERROR((F16*J16)*N16,"") -> 3052.35 | S16: =IFERROR(O16-Y16,"") -> 2894 | T16: =IFERROR(P16-Z16,"") -> 0 | U16: =IFERROR(Q16-AA16,"") -> 0 | V16: =IFERROR(R16-AB16,"") -> 2934.1784 | W16: =IFERROR(S16/K16,"") -> 0.0413946 | X16: =S16/D16 -> 0.0008638806 | Y16: =Brokerage(F16, L16, G16) -> 158.35 | Z16: =IF(H16=0,0,CAPITAL!$H$5*Y16) -> 0 | AA16: =IF(I16=0,0,CAPITAL!$H$6*Y16) -> 0 | AB16: =IF(J16=0,0,CAPITAL!$H$7*Y16) -> 118.17164
A17: MAHKTECH | B17: 9 | C17: =ENTRY!B11 -> SILVERBEES | D17: =CAPITAL!$C$2 -> 3350000 | E17: =ENTRY!C11 -> 46038 | F17: =ENTRY!D11 -> 269.3 | G17: =ENTRY!E11 -> 259 | H17: =G17*ENTRY!$O11 -> 0 | I17: =G17*ENTRY!$P11 -> 0 | J17: =G17*ENTRY!$Q11 -> 259 | K17: =F17*G17 -> 69748.7 | L17: =ENTRY!F11 -> 280.95 | M17: =ENTRY!G11 -> 46041 | N17: =IFERROR(((L17-F17)*G17)/K17,"") -> 0.043260304 | O17: =IFERROR(N17*K17,"") -> 3017.35 | P17: =IFERROR((F17*H17)*N17,"") -> 0 | Q17: =IFERROR((F17*I17)*N17,"") -> 0 | R17: =IFERROR((F17*J17)*N17,"") -> 3017.35 | S17: =IFERROR(O17-Y17,"") -> 2859.02 | T17: =IFERROR(P17-Z17,"") -> 0 | U17: =IFERROR(Q17-AA17,"") -> 0 | V17: =IFERROR(R17-AB17,"") -> 2899.1933 | W17: =IFERROR(S17/K17,"") -> 0.040990298 | X17: =IFERROR(S17/D17,"") -> 0.00085343881 | Y17: =Brokerage(F17, L17, G17) -> 158.33 | Z17: =IF(H17=0,0,CAPITAL!$H$5*Y17) -> 0 | AA17: =IF(I17=0,0,CAPITAL!$H$6*Y17) -> 0 | AB17: =IF(J17=0,0,CAPITAL!$H$7*Y17) -> 118.15672
A18: HDFCGROWTH | B18: 10 | C18: =ENTRY!B12 -> SILVER LIFE (ADITYA BIRLA) | D18: =CAPITAL!$C$2 -> 3350000 | E18: =ENTRY!C12 -> 46041 | F18: =ENTRY!D12 -> 292.94 | G18: =ENTRY!E12 -> 238 | H18: =G18*ENTRY!$O12 -> 0 | I18: =G18*ENTRY!$P12 -> 0 | J18: =G18*ENTRY!$Q12 -> 238 | K18: =F18*G18 -> 69719.72 | L18: =ENTRY!F12 -> 311.85 | M18: =ENTRY!G12 -> 46042 | N18: =IFERROR(((L18-F18)*G18)/K18,"") -> 0.064552468 | O18: =IFERROR(N18*K18,"") -> 4500.58 | P18: =IFERROR((F18*H18)*N18,"") -> 0 | Q18: =IFERROR((F18*I18)*N18,"") -> 0 | R18: =IFERROR((F18*J18)*N18,"") -> 4500.58 | S18: =IFERROR(O18-Y18,"") -> 4341.2 | T18: =IFERROR(P18-Z18,"") -> 0 | U18: =IFERROR(Q18-AA18,"") -> 0 | V18: =IFERROR(R18-AB18,"") -> 4381.6397 | W18: =IFERROR(S18/K18,"") -> 0.062266458 | X18: =S18/D18 -> 0.0012958806 | Y18: =Brokerage(F18, L18, G18) -> 159.38 | Z18: =IF(H18=0,0,CAPITAL!$H$5*Y18) -> 0 | AA18: =IF(I18=0,0,CAPITAL!$H$6*Y18) -> 0 | AB18: =IF(J18=0,0,CAPITAL!$H$7*Y18) -> 118.9403
A19: LOWVOLIETF | B19: 11 | C19: =ENTRY!B13 -> TWCGOLD TEF | D19: =CAPITAL!$C$2 -> 3350000 | E19: =ENTRY!C13 -> 46042 | F19: =ENTRY!D13 -> 148.5 | G19: =ENTRY!E13 -> 473 | H19: =G19*ENTRY!$O13 -> 0 | I19: =G19*ENTRY!$P13 -> 0 | J19: =G19*ENTRY!$Q13 -> 473 | K19: =F19*G19 -> 70240.5 | L19: =ENTRY!F13 -> 158.07 | M19: =ENTRY!G13 -> 46043 | N19: =IFERROR(((L19-F19)*G19)/K19,"") -> 0.064444444 | O19: =IFERROR(N19*K19,"") -> 4526.61 | P19: =IFERROR((F19*H19)*N19,"") -> 0 | Q19: =IFERROR((F19*I19)*N19,"") -> 0 | R19: =IFERROR((F19*J19)*N19,"") -> 4526.61 | S19: =IFERROR(O19-Y19,"") -> 4365.18 | T19: =IFERROR(P19-Z19,"") -> 0 | U19: =IFERROR(Q19-AA19,"") -> 0 | V19: =IFERROR(R19-AB19,"") -> 4406.1399 | W19: =IFERROR(S19/K19,"") -> 0.062146198 | X19: =IFERROR(S19/D19,"") -> 0.0013030388 | Y19: =Brokerage(F19, L19, G19) -> 161.43 | Z19: =IF(H19=0,0,CAPITAL!$H$5*Y19) -> 0 | AA19: =IF(I19=0,0,CAPITAL!$H$6*Y19) -> 0 | AB19: =IF(J19=0,0,CAPITAL!$H$7*Y19) -> 120.47015
A20: HDFCQUAL | B20: 12 | C20: =ENTRY!B14 -> SILVERBAND (BANDHAN BANK) | D20: =CAPITAL!$C$2 -> 3350000 | E20: =ENTRY!C14 -> 46042 | F20: =ENTRY!D14 -> 326.44 | G20: =ENTRY!E14 -> 522 | H20: =G20*ENTRY!$O14 -> 0 | I20: =G20*ENTRY!$P14 -> 0 | J20: =G20*ENTRY!$Q14 -> 522 | K20: =F20*G20 -> 170401.68 | L20: =ENTRY!F14 -> LIVE | M20: =ENTRY!G14 | N20: =IFERROR(((L20-F20)*G20)/K20,"") | O20: =IFERROR(N20*K20,"") -> 0 | P20: =IFERROR((F20*H20)*N20,"") -> 0 | Q20: =IFERROR((F20*I20)*N20,"") -> 0 | R20: =IFERROR((F20*J20)*N20,"") -> 0 | S20: =IFERROR(O20-Y20,"") | T20: =IFERROR(P20-Z20,"") -> 0 | U20: =IFERROR(Q20-AA20,"") -> 0 | V20: =IFERROR(R20-AB20,"") | W20: =IFERROR(S20/K20,"") -> 0 | X20: =S20/D20 -> 0 | Y20: =Brokerage(F20, L20, G20) -> ERR | Z20: =IF(H20=0,0,CAPITAL!$H$5*Y20) -> 0 | AA20: =IF(I20=0,0,CAPITAL!$H$6*Y20) -> 0 | AB20: =IF(J20=0,0,CAPITAL!$H$7*Y20) -> #VALUE!
A21: BSE500IETF | B21: 13 | C21: =ENTRY!B15 -> SILVERBEES | D21: =CAPITAL!$C$2 -> 3350000 | E21: =ENTRY!C15 -> 46043 | F21: =ENTRY!D15 -> 304.57 | G21: =ENTRY!E15 -> 473 | H21: =G21*ENTRY!$O15 -> 0 | I21: =G21*ENTRY!$P15 -> 0 | J21: =G21*ENTRY!$Q15 -> 473 | K21: =F21*G21 -> 144061.61 | L21: =ENTRY!F15 -> 315.56 | M21: =ENTRY!G15 -> 46049 | N21: =IFERROR(((L21-F21)*G21)/K21,"") -> 0.036083659 | O21: =IFERROR(N21*K21,"") -> 5198.27 | P21: =IFERROR((F21*H21)*N21,"") -> 0 | Q21: =IFERROR((F21*I21)*N21,"") -> 0 | R21: =IFERROR((F21*J21)*N21,"") -> 5198.27 | S21: =IFERROR(O21-Y21,"") -> 4872.31 | T21: =IFERROR(P21-Z21,"") -> 0 | U21: =IFERROR(Q21-AA21,"") -> 0 | V21: =IFERROR(R21-AB21,"") -> 4955.0163 | W21: =IFERROR(S21/K21,"") -> 0.033821016 | X21: =IFERROR(S21/D21,"") -> 0.0014544209 | Y21: =Brokerage(F21, L21, G21) -> 325.96 | Z21: =IF(H21=0,0,CAPITAL!$H$5*Y21) -> 0 | AA21: =IF(I21=0,0,CAPITAL!$H$6*Y21) -> 0 | AB21: =IF(J21=0,0,CAPITAL!$H$7*Y21) -> 243.25373
A22: COMMOIETF | B22: 14 | C22: =ENTRY!B16 -> SILVERBAND (BANDHAN BANK) | D22: =CAPITAL!$C$2 -> 3350000 | E22: =ENTRY!C16 -> 46044 | F22: =ENTRY!D16 -> 295.2 | G22: =ENTRY!E16 -> 237 | H22: =G22*ENTRY!$O16 -> 0 | I22: =G22*ENTRY!$P16 -> 0 | J22: =G22*ENTRY!$Q16 -> 237 | K22: =F22*G22 -> 69962.4 | L22: =ENTRY!F16 -> LIVE | M22: =ENTRY!G16 | N22: =IFERROR(((L22-F22)*G22)/K22,"") | O22: =IFERROR(N22*K22,"") -> 0 | P22: =IFERROR((F22*H22)*N22,"") -> 0 | Q22: =IFERROR((F22*I22)*N22,"") -> 0 | R22: =IFERROR((F22*J22)*N22,"") -> 0 | S22: =IFERROR(O22-Y22,"") | T22: =IFERROR(P22-Z22,"") -> 0 | U22: =IFERROR(Q22-AA22,"") -> 0 | V22: =IFERROR(R22-AB22,"") | W22: =IFERROR(S22/K22,"") -> 0 | X22: =S22/D22 -> 0 | Y22: =Brokerage(F22, L22, G22) -> ERR | Z22: =IF(H22=0,0,CAPITAL!$H$5*Y22) -> 0 | AA22: =IF(I22=0,0,CAPITAL!$H$6*Y22) -> 0 | AB22: =IF(J22=0,0,CAPITAL!$H$7*Y22) -> #VALUE!
A23: FINIETF | B23: 15 | C23: =ENTRY!B17 -> SILVERBEES | D23: =CAPITAL!$C$2 -> 3350000 | E23: =ENTRY!C17 -> 46044 | F23: =ENTRY!D17 -> 271.82 | G23: =ENTRY!E17 -> 257 | H23: =G23*ENTRY!$O17 -> 0 | I23: =G23*ENTRY!$P17 -> 0 | J23: =G23*ENTRY!$Q17 -> 257 | K23: =F23*G23 -> 69857.74 | L23: =ENTRY!F17 -> 315.56 | M23: =ENTRY!G17 -> 46049 | N23: =IFERROR(((L23-F23)*G23)/K23,"") -> 0.16091531 | O23: =IFERROR(N23*K23,"") -> 11241.18 | P23: =IFERROR((F23*H23)*N23,"") -> 0 | Q23: =IFERROR((F23*I23)*N23,"") -> 0 | R23: =IFERROR((F23*J23)*N23,"") -> 11241.18 | S23: =IFERROR(O23-Y23,"") -> 11074.54 | T23: =IFERROR(P23-Z23,"") -> 0 | U23: =IFERROR(Q23-AA23,"") -> 0 | V23: =IFERROR(R23-AB23,"") -> 11116.822 | W23: =IFERROR(S23/K23,"") -> 0.15852989 | X23: =IFERROR(S23/D23,"") -> 0.0033058328 | Y23: =Brokerage(F23, L23, G23) -> 166.64 | Z23: =IF(H23=0,0,CAPITAL!$H$5*Y23) -> 0 | AA23: =IF(I23=0,0,CAPITAL!$H$6*Y23) -> 0 | AB23: =IF(J23=0,0,CAPITAL!$H$7*Y23) -> 124.35821
A24: INFRAIETF | B24: 16 | C24: =ENTRY!B18 -> SILVERBEES | D24: =CAPITAL!$C$2 -> 3350000 | E24: =ENTRY!C18 | F24: =ENTRY!D18 | G24: =ENTRY!E18 | H24: =G24*ENTRY!$O18 -> 0 | I24: =G24*ENTRY!$P18 -> 0 | J24: =G24*ENTRY!$Q18 -> 0 | K24: =F24*G24 -> 0 | L24: =ENTRY!F18 | M24: =ENTRY!G18 | N24: =IFERROR(((L24-F24)*G24)/K24,"") | O24: =IFERROR(N24*K24,"") -> 0 | P24: =IFERROR((F24*H24)*N24,"") -> 0 | Q24: =IFERROR((F24*I24)*N24,"") -> 0 | R24: =IFERROR((F24*J24)*N24,"") -> 0 | S24: =IFERROR(O24-Y24,"") | T24: =IFERROR(P24-Z24,"") -> 0 | U24: =IFERROR(Q24-AA24,"") -> 0 | V24: =IFERROR(R24-AB24,"") -> 0 | W24: =IFERROR(S24/K24,"") | X24: =S24/D24 -> 0 | Y24: =Brokerage(F24, L24, G24) -> ERR | Z24: =IF(H24=0,0,CAPITAL!$H$5*Y24) -> 0 | AA24: =IF(I24=0,0,CAPITAL!$H$6*Y24) -> 0 | AB24: =IF(J24=0,0,CAPITAL!$H$7*Y24) -> 0
A25: MNC | B25: 17 | C25: =ENTRY!B19 -> SILVERBEES | D25: =CAPITAL!$C$2 -> 3350000 | E25: =ENTRY!C19 | F25: =ENTRY!D19 | G25: =ENTRY!E19 | H25: =G25*ENTRY!$O19 -> 0 | I25: =G25*ENTRY!$P19 -> 0 | J25: =G25*ENTRY!$Q19 -> 0 | K25: =F25*G25 -> 0 | L25: =ENTRY!F19 | M25: =ENTRY!G19 | N25: =IFERROR(((L25-F25)*G25)/K25,"") | O25: =IFERROR(N25*K25,"") -> 0 | P25: =IFERROR((F25*H25)*N25,"") -> 0 | Q25: =IFERROR((F25*I25)*N25,"") -> 0 | R25: =IFERROR((F25*J25)*N25,"") -> 0 | S25: =IFERROR(O25-Y25,"") | T25: =IFERROR(P25-Z25,"") -> 0 | U25: =IFERROR(Q25-AA25,"") -> 0 | V25: =IFERROR(R25-AB25,"") -> 0 | W25: =IFERROR(S25/K25,"") | X25: =IFERROR(S25/D25,"") -> 0 | Y25: =Brokerage(F25, L25, G25) -> ERR | Z25: =IF(H25=0,0,CAPITAL!$H$5*Y25) -> 0 | AA25: =IF(I25=0,0,CAPITAL!$H$6*Y25) -> 0 | AB25: =IF(J25=0,0,CAPITAL!$H$7*Y25) -> 0
A26: ALPHAETF | B26: 17 | C26: =ENTRY!B20 -> SILVERBEES | D26: =CAPITAL!$C$2 -> 3350000 | E26: =ENTRY!C20 | F26: =ENTRY!D20 | G26: =ENTRY!E20 | H26: =G26*ENTRY!$O20 -> 0 | I26: =G26*ENTRY!$P20 -> 0 | J26: =G26*ENTRY!$Q20 -> 0 | K26: =F26*G26 -> 0 | L26: =ENTRY!F20 | M26: =ENTRY!G20 | N26: =IFERROR(((L26-F26)*G26)/K26,"") | O26: =IFERROR(N26*K26,"") -> 0 | P26: =IFERROR((F26*H26)*N26,"") -> 0 | Q26: =IFERROR((F26*I26)*N26,"") -> 0 | R26: =IFERROR((F26*J26)*N26,"") -> 0 | S26: =IFERROR(O26-Y26,"") | T26: =IFERROR(P26-Z26,"") -> 0 | U26: =IFERROR(Q26-AA26,"") -> 0 | V26: =IFERROR(R26-AB26,"") -> 0 | W26: =IFERROR(S26/K26,"") | X26: =S26/D26 -> 0 | Y26: =Brokerage(F26, L26, G26) -> ERR | Z26: =IF(H26=0,0,CAPITAL!$H$5*Y26) -> 0 | AA26: =IF(I26=0,0,CAPITAL!$H$6*Y26) -> 0 | AB26: =IF(J26=0,0,CAPITAL!$H$7*Y26) -> 0
A27: MIDSMALL | B27: 19 | C27: =ENTRY!B21 -> SILVERBEES | D27: =CAPITAL!$C$2 -> 3350000 | E27: =ENTRY!C21 | F27: =ENTRY!D21 | G27: =ENTRY!E21 | H27: =G27*ENTRY!$O21 -> 0 | I27: =G27*ENTRY!$P21 -> 0 | J27: =G27*ENTRY!$Q21 -> 0 | K27: =F27*G27 -> 0 | L27: =ENTRY!F21 | M27: =ENTRY!G21 | N27: =IFERROR(((L27-F27)*G27)/K27,"") | O27: =IFERROR(N27*K27,"") -> 0 | P27: =IFERROR((F27*H27)*N27,"") -> 0 | Q27: =IFERROR((F27*I27)*N27,"") -> 0 | R27: =IFERROR((F27*J27)*N27,"") -> 0 | S27: =IFERROR(O27-Y27,"") | T27: =IFERROR(P27-Z27,"") -> 0 | U27: =IFERROR(Q27-AA27,"") -> 0 | V27: =IFERROR(R27-AB27,"") -> 0 | W27: =IFERROR(S27/K27,"") | X27: =IFERROR(S27/D27,"") -> 0 | Y27: =Brokerage(F27, L27, G27) -> ERR | Z27: =IF(H27=0,0,CAPITAL!$H$5*Y27) -> 0 | AA27: =IF(I27=0,0,CAPITAL!$H$6*Y27) -> 0 | AB27: =IF(J27=0,0,CAPITAL!$H$7*Y27) -> 0
A28: SMALLCAP | B28: 20 | C28: =ENTRY!B22 -> SILVERBEES | D28: =CAPITAL!$C$2 -> 3350000 | E28: =ENTRY!C22 | F28: =ENTRY!D22 | G28: =ENTRY!E22 | H28: =G28*ENTRY!$O22 -> 0 | I28: =G28*ENTRY!$P22 -> 0 | J28: =G28*ENTRY!$Q22 -> 0 | K28: =F28*G28 -> 0 | L28: =ENTRY!F22 | M28: =ENTRY!G22 | N28: =IFERROR(((L28-F28)*G28)/K28,"") | O28: =IFERROR(N28*K28,"") -> 0 | P28: =IFERROR((F28*H28)*N28,"") -> 0 | Q28: =IFERROR((F28*I28)*N28,"") -> 0 | R28: =IFERROR((F28*J28)*N28,"") -> 0 | S28: =IFERROR(O28-Y28,"") | T28: =IFERROR(P28-Z28,"") -> 0 | U28: =IFERROR(Q28-AA28,"") -> 0 | V28: =IFERROR(R28-AB28,"") -> 0 | W28: =IFERROR(S28/K28,"") | X28: =S28/D28 -> 0 | Y28: =Brokerage(F28, L28, G28) -> ERR | Z28: =IF(H28=0,0,CAPITAL!$H$5*Y28) -> 0 | AA28: =IF(I28=0,0,CAPITAL!$H$6*Y28) -> 0 | AB28: =IF(J28=0,0,CAPITAL!$H$7*Y28) -> 0
A29: MONIFTY500 | B29: 21 | C29: =ENTRY!B23 -> SILVERBEES | D29: =CAPITAL!$C$2 -> 3350000 | E29: =ENTRY!C23 | F29: =ENTRY!D23 | G29: =ENTRY!E23 | H29: =G29*ENTRY!$O23 -> 0 | I29: =G29*ENTRY!$P23 -> 0 | J29: =G29*ENTRY!$Q23 -> 0 | K29: =F29*G29 -> 0 | L29: =ENTRY!F23 | M29: =ENTRY!G23 | N29: =IFERROR(((L29-F29)*G29)/K29,"") | O29: =IFERROR(N29*K29,"") -> 0 | P29: =IFERROR((F29*H29)*N29,"") -> 0 | Q29: =IFERROR((F29*I29)*N29,"") -> 0 | R29: =IFERROR((F29*J29)*N29,"") -> 0 | S29: =IFERROR(O29-Y29,"") | T29: =IFERROR(P29-Z29,"") -> 0 | U29: =IFERROR(Q29-AA29,"") -> 0 | V29: =IFERROR(R29-AB29,"") -> 0 | W29: =IFERROR(S29/K29,"") | X29: =IFERROR(S29/D29,"") -> 0 | Y29: =Brokerage(F29, L29, G29) -> ERR | Z29: =IF(H29=0,0,CAPITAL!$H$5*Y29) -> 0 | AA29: =IF(I29=0,0,CAPITAL!$H$6*Y29) -> 0 | AB29: =IF(J29=0,0,CAPITAL!$H$7*Y29) -> 0
A30: MOREALTY | B30: 22 | C30: =ENTRY!B24 -> SILVERBEES | D30: =CAPITAL!$C$2 -> 3350000 | E30: =ENTRY!C24 | F30: =ENTRY!D24 | G30: =ENTRY!E24 | H30: =G30*ENTRY!$O24 -> 0 | I30: =G30*ENTRY!$P24 -> 0 | J30: =G30*ENTRY!$Q24 -> 0 | K30: =F30*G30 -> 0 | L30: =ENTRY!F24 | M30: =ENTRY!G24 | N30: =IFERROR(((L30-F30)*G30)/K30,"") | O30: =IFERROR(N30*K30,"") -> 0 | P30: =IFERROR((F30*H30)*N30,"") -> 0 | Q30: =IFERROR((F30*I30)*N30,"") -> 0 | R30: =IFERROR((F30*J30)*N30,"") -> 0 | S30: =IFERROR(O30-Y30,"") | T30: =IFERROR(P30-Z30,"") -> 0 | U30: =IFERROR(Q30-AA30,"") -> 0 | V30: =IFERROR(R30-AB30,"") -> 0 | W30: =IFERROR(S30/K30,"") | X30: =S30/D30 -> 0 | Y30: =Brokerage(F30, L30, G30) -> ERR | Z30: =IF(H30=0,0,CAPITAL!$H$5*Y30) -> 0 | AA30: =IF(I30=0,0,CAPITAL!$H$6*Y30) -> 0 | AB30: =IF(J30=0,0,CAPITAL!$H$7*Y30) -> 0
A31: MOSMALL250 | B31: 23 | C31: =ENTRY!B25 -> SILVERBEES | D31: =CAPITAL!$C$2 -> 3350000 | E31: =ENTRY!C25 | F31: =ENTRY!D25 | G31: =ENTRY!E25 | H31: =G31*ENTRY!$O25 -> 0 | I31: =G31*ENTRY!$P25 -> 0 | J31: =G31*ENTRY!$Q25 -> 0 | K31: =F31*G31 -> 0 | L31: =ENTRY!F25 | M31: =ENTRY!G25 | N31: =IFERROR(((L31-F31)*G31)/K31,"") | O31: =IFERROR(N31*K31,"") -> 0 | P31: =IFERROR((F31*H31)*N31,"") -> 0 | Q31: =IFERROR((F31*I31)*N31,"") -> 0 | R31: =IFERROR((F31*J31)*N31,"") -> 0 | S31: =IFERROR(O31-Y31,"") | T31: =IFERROR(P31-Z31,"") -> 0 | U31: =IFERROR(Q31-AA31,"") -> 0 | V31: =IFERROR(R31-AB31,"") -> 0 | W31: =IFERROR(S31/K31,"") | X31: =IFERROR(S31/D31,"") -> 0 | Y31: =Brokerage(F31, L31, G31) -> ERR | Z31: =IF(H31=0,0,CAPITAL!$H$5*Y31) -> 0 | AA31: =IF(I31=0,0,CAPITAL!$H$6*Y31) -> 0 | AB31: =IF(J31=0,0,CAPITAL!$H$7*Y31) -> 0
A32: MOVALUE | B32: 24 | C32: =ENTRY!B26 -> SILVERBEES | D32: =CAPITAL!$C$2 -> 3350000 | E32: =ENTRY!C26 | F32: =ENTRY!D26 | G32: =ENTRY!E26 | H32: =G32*ENTRY!$O26 -> 0 | I32: =G32*ENTRY!$P26 -> 0 | J32: =G32*ENTRY!$Q26 -> 0 | K32: =F32*G32 -> 0 | L32: =ENTRY!F26 | M32: =ENTRY!G26 | N32: =IFERROR(((L32-F32)*G32)/K32,"") | O32: =IFERROR(N32*K32,"") -> 0 | P32: =IFERROR((F32*H32)*N32,"") -> 0 | Q32: =IFERROR((F32*I32)*N32,"") -> 0 | R32: =IFERROR((F32*J32)*N32,"") -> 0 | S32: =IFERROR(O32-Y32,"") | T32: =IFERROR(P32-Z32,"") -> 0 | U32: =IFERROR(Q32-AA32,"") -> 0 | V32: =IFERROR(R32-AB32,"") -> 0 | W32: =IFERROR(S32/K32,"") | X32: =S32/D32 -> 0 | Y32: =Brokerage(F32, L32, G32) -> ERR | Z32: =IF(H32=0,0,CAPITAL!$H$5*Y32) -> 0 | AA32: =IF(I32=0,0,CAPITAL!$H$6*Y32) -> 0 | AB32: =IF(J32=0,0,CAPITAL!$H$7*Y32) -> 0
A33: MONQ50 | B33: 25 | C33: =ENTRY!B27 -> SILVERBEES | D33: =CAPITAL!$C$2 -> 3350000 | E33: =ENTRY!C27 | F33: =ENTRY!D27 | G33: =ENTRY!E27 | H33: =G33*ENTRY!$O27 -> 0 | I33: =G33*ENTRY!$P27 -> 0 | J33: =G33*ENTRY!$Q27 -> 0 | K33: =F33*G33 -> 0 | L33: =ENTRY!F27 | M33: =ENTRY!G27 | N33: =IFERROR(((L33-F33)*G33)/K33,"") | O33: =IFERROR(N33*K33,"") -> 0 | P33: =IFERROR((F33*H33)*N33,"") -> 0 | Q33: =IFERROR((F33*I33)*N33,"") -> 0 | R33: =IFERROR((F33*J33)*N33,"") -> 0 | S33: =IFERROR(O33-Y33,"") | T33: =IFERROR(P33-Z33,"") -> 0 | U33: =IFERROR(Q33-AA33,"") -> 0 | V33: =IFERROR(R33-AB33,"") -> 0 | W33: =IFERROR(S33/K33,"") | X33: =IFERROR(S33/D33,"") -> 0 | Y33: =Brokerage(F33, L33, G33) -> ERR | Z33: =IF(H33=0,0,CAPITAL!$H$5*Y33) -> 0 | AA33: =IF(I33=0,0,CAPITAL!$H$6*Y33) -> 0 | AB33: =IF(J33=0,0,CAPITAL!$H$7*Y33) -> 0
A34: MON100 | B34: 26 | C34: =ENTRY!B28 -> SILVERBEES | D34: =CAPITAL!$C$2 -> 3350000 | E34: =ENTRY!C28 | F34: =ENTRY!D28 | G34: =ENTRY!E28 | H34: =G34*ENTRY!$O28 -> 0 | I34: =G34*ENTRY!$P28 -> 0 | J34: =G34*ENTRY!$Q28 -> 0 | K34: =F34*G34 -> 0 | L34: =ENTRY!F28 | M34: =ENTRY!G28 | N34: =IFERROR(((L34-F34)*G34)/K34,"") | O34: =IFERROR(N34*K34,"") -> 0 | P34: =IFERROR((F34*H34)*N34,"") -> 0 | Q34: =IFERROR((F34*I34)*N34,"") -> 0 | R34: =IFERROR((F34*J34)*N34,"") -> 0 | S34: =IFERROR(O34-Y34,"") | T34: =IFERROR(P34-Z34,"") -> 0 | U34: =IFERROR(Q34-AA34,"") -> 0 | V34: =IFERROR(R34-AB34,"") -> 0 | W34: =IFERROR(S34/K34,"") | X34: =S34/D34 -> 0 | Y34: =Brokerage(F34, L34, G34) -> ERR | Z34: =IF(H34=0,0,CAPITAL!$H$5*Y34) -> 0 | AA34: =IF(I34=0,0,CAPITAL!$H$6*Y34) -> 0 | AB34: =IF(J34=0,0,CAPITAL!$H$7*Y34) -> 0
A35: TOP100CASE | B35: 27 | C35: =ENTRY!B29 -> SILVERBEES | D35: =CAPITAL!$C$2 -> 3350000 | E35: =ENTRY!C29 | F35: =ENTRY!D29 | G35: =ENTRY!E29 | H35: =G35*ENTRY!$O29 -> 0 | I35: =G35*ENTRY!$P29 -> 0 | J35: =G35*ENTRY!$Q29 -> 0 | K35: =F35*G35 -> 0 | L35: =ENTRY!F29 | M35: =ENTRY!G29 | N35: =IFERROR(((L35-F35)*G35)/K35,"") | O35: =IFERROR(N35*K35,"") -> 0 | P35: =IFERROR((F35*H35)*N35,"") -> 0 | Q35: =IFERROR((F35*I35)*N35,"") -> 0 | R35: =IFERROR((F35*J35)*N35,"") -> 0 | S35: =IFERROR(O35-Y35,"") | T35: =IFERROR(P35-Z35,"") -> 0 | U35: =IFERROR(Q35-AA35,"") -> 0 | V35: =IFERROR(R35-AB35,"") -> 0 | W35: =IFERROR(S35/K35,"") | X35: =IFERROR(S35/D35,"") -> 0 | Y35: =Brokerage(F35, L35, G35) -> ERR | Z35: =IF(H35=0,0,CAPITAL!$H$5*Y35) -> 0 | AA35: =IF(I35=0,0,CAPITAL!$H$6*Y35) -> 0 | AB35: =IF(J35=0,0,CAPITAL!$H$7*Y35) -> 0
A36: NIFTYBEES | B36: 28 | C36: =ENTRY!B30 -> SILVERBEES | D36: =CAPITAL!$C$2 -> 3350000 | E36: =ENTRY!C30 | F36: =ENTRY!D30 | G36: =ENTRY!E30 | H36: =G36*ENTRY!$O30 -> 0 | I36: =G36*ENTRY!$P30 -> 0 | J36: =G36*ENTRY!$Q30 -> 0 | K36: =F36*G36 -> 0 | L36: =ENTRY!F30 | M36: =ENTRY!G30 | N36: =IFERROR(((L36-F36)*G36)/K36,"") | O36: =IFERROR(N36*K36,"") -> 0 | P36: =IFERROR((F36*H36)*N36,"") -> 0 | Q36: =IFERROR((F36*I36)*N36,"") -> 0 | R36: =IFERROR((F36*J36)*N36,"") -> 0 | S36: =IFERROR(O36-Y36,"") | T36: =IFERROR(P36-Z36,"") -> 0 | U36: =IFERROR(Q36-AA36,"") -> 0 | V36: =IFERROR(R36-AB36,"") -> 0 | W36: =IFERROR(S36/K36,"") | X36: =S36/D36 -> 0 | Y36: =Brokerage(F36, L36, G36) -> ERR | Z36: =IF(H36=0,0,CAPITAL!$H$5*Y36) -> 0 | AA36: =IF(I36=0,0,CAPITAL!$H$6*Y36) -> 0 | AB36: =IF(J36=0,0,CAPITAL!$H$7*Y36) -> 0
A37: MOMENTUM50 | B37: 29 | C37: =ENTRY!B31 -> SILVERBEES | D37: =CAPITAL!$C$2 -> 3350000 | E37: =ENTRY!C31 | F37: =ENTRY!D31 | G37: =ENTRY!E31 | H37: =G37*ENTRY!$O31 -> 0 | I37: =G37*ENTRY!$P31 -> 0 | J37: =G37*ENTRY!$Q31 -> 0 | K37: =F37*G37 -> 0 | L37: =ENTRY!F31 | M37: =ENTRY!G31 | N37: =IFERROR(((L37-F37)*G37)/K37,"") | O37: =IFERROR(N37*K37,"") -> 0 | P37: =IFERROR((F37*H37)*N37,"") -> 0 | Q37: =IFERROR((F37*I37)*N37,"") -> 0 | R37: =IFERROR((F37*J37)*N37,"") -> 0 | S37: =IFERROR(O37-Y37,"") | T37: =IFERROR(P37-Z37,"") -> 0 | U37: =IFERROR(Q37-AA37,"") -> 0 | V37: =IFERROR(R37-AB37,"") -> 0 | W37: =IFERROR(S37/K37,"") | X37: =IFERROR(S37/D37,"") -> 0 | Y37: =Brokerage(F37, L37, G37) -> ERR | Z37: =IF(H37=0,0,CAPITAL!$H$5*Y37) -> 0 | AA37: =IF(I37=0,0,CAPITAL!$H$6*Y37) -> 0 | AB37: =IF(J37=0,0,CAPITAL!$H$7*Y37) -> 0
A38: ALPHA | B38: 30 | C38: =ENTRY!B32 -> SILVERBEES | D38: =CAPITAL!$C$2 -> 3350000 | E38: =ENTRY!C32 | F38: =ENTRY!D32 | G38: =ENTRY!E32 | H38: =G38*ENTRY!$O32 -> 0 | I38: =G38*ENTRY!$P32 -> 0 | J38: =G38*ENTRY!$Q32 -> 0 | K38: =F38*G38 -> 0 | L38: =ENTRY!F32 | M38: =ENTRY!G32 | N38: =IFERROR(((L38-F38)*G38)/K38,"") | O38: =IFERROR(N38*K38,"") -> 0 | P38: =IFERROR((F38*H38)*N38,"") -> 0 | Q38: =IFERROR((F38*I38)*N38,"") -> 0 | R38: =IFERROR((F38*J38)*N38,"") -> 0 | S38: =IFERROR(O38-Y38,"") | T38: =IFERROR(P38-Z38,"") -> 0 | U38: =IFERROR(Q38-AA38,"") -> 0 | V38: =IFERROR(R38-AB38,"") -> 0 | W38: =IFERROR(S38/K38,"") | X38: =S38/D38 -> 0 | Y38: =Brokerage(F38, L38, G38) -> ERR | Z38: =IF(H38=0,0,CAPITAL!$H$5*Y38) -> 0 | AA38: =IF(I38=0,0,CAPITAL!$H$6*Y38) -> 0 | AB38: =IF(J38=0,0,CAPITAL!$H$7*Y38) -> 0
A39: ALPL30IETF | B39: 31 | C39: =ENTRY!B33 -> SILVERBEES | D39: =CAPITAL!$C$2 -> 3350000 | E39: =ENTRY!C33 | F39: =ENTRY!D33 | G39: =ENTRY!E33 | H39: =G39*ENTRY!$O33 -> 0 | I39: =G39*ENTRY!$P33 -> 0 | J39: =G39*ENTRY!$Q33 -> 0 | K39: =F39*G39 -> 0 | L39: =ENTRY!F33 | M39: =ENTRY!G33 | N39: =IFERROR(((L39-F39)*G39)/K39,"") | O39: =IFERROR(N39*K39,"") -> 0 | P39: =IFERROR((F39*H39)*N39,"") -> 0 | Q39: =IFERROR((F39*I39)*N39,"") -> 0 | R39: =IFERROR((F39*J39)*N39,"") -> 0 | S39: =IFERROR(O39-Y39,"") | T39: =IFERROR(P39-Z39,"") -> 0 | U39: =IFERROR(Q39-AA39,"") -> 0 | V39: =IFERROR(R39-AB39,"") -> 0 | W39: =IFERROR(S39/K39,"") | X39: =IFERROR(S39/D39,"") -> 0 | Y39: =Brokerage(F39, L39, G39) -> ERR | Z39: =IF(H39=0,0,CAPITAL!$H$5*Y39) -> 0 | AA39: =IF(I39=0,0,CAPITAL!$H$6*Y39) -> 0 | AB39: =IF(J39=0,0,CAPITAL!$H$7*Y39) -> 0
A40: AUTOIETF | B40: 32 | C40: =ENTRY!B34 -> SILVERBEES | D40: =CAPITAL!$C$2 -> 3350000 | E40: =ENTRY!C34 | F40: =ENTRY!D34 | G40: =ENTRY!E34 | H40: =G40*ENTRY!$O34 -> 0 | I40: =G40*ENTRY!$P34 -> 0 | J40: =G40*ENTRY!$Q34 -> 0 | K40: =F40*G40 -> 0 | L40: =ENTRY!F34 | M40: =ENTRY!G34 | N40: =IFERROR(((L40-F40)*G40)/K40,"") | O40: =IFERROR(N40*K40,"") -> 0 | P40: =IFERROR((F40*H40)*N40,"") -> 0 | Q40: =IFERROR((F40*I40)*N40,"") -> 0 | R40: =IFERROR((F40*J40)*N40,"") -> 0 | S40: =IFERROR(O40-Y40,"") | T40: =IFERROR(P40-Z40,"") -> 0 | U40: =IFERROR(Q40-AA40,"") -> 0 | V40: =IFERROR(R40-AB40,"") -> 0 | W40: =IFERROR(S40/K40,"") | X40: =S40/D40 -> 0 | Y40: =Brokerage(F40, L40, G40) -> ERR | Z40: =IF(H40=0,0,CAPITAL!$H$5*Y40) -> 0 | AA40: =IF(I40=0,0,CAPITAL!$H$6*Y40) -> 0 | AB40: =IF(J40=0,0,CAPITAL!$H$7*Y40) -> 0
A41: BANKBEES | B41: 33 | C41: =ENTRY!B35 -> SILVERBEES | D41: =CAPITAL!$C$2 -> 3350000 | E41: =ENTRY!C35 | F41: =ENTRY!D35 | G41: =ENTRY!E35 | H41: =G41*ENTRY!$O35 -> 0 | I41: =G41*ENTRY!$P35 -> 0 | J41: =G41*ENTRY!$Q35 -> 0 | K41: =F41*G41 -> 0 | L41: =ENTRY!F35 | M41: =ENTRY!G35 | N41: =IFERROR(((L41-F41)*G41)/K41,"") | O41: =IFERROR(N41*K41,"") -> 0 | P41: =IFERROR((F41*H41)*N41,"") -> 0 | Q41: =IFERROR((F41*I41)*N41,"") -> 0 | R41: =IFERROR((F41*J41)*N41,"") -> 0 | S41: =IFERROR(O41-Y41,"") | T41: =IFERROR(P41-Z41,"") -> 0 | U41: =IFERROR(Q41-AA41,"") -> 0 | V41: =IFERROR(R41-AB41,"") -> 0 | W41: =IFERROR(S41/K41,"") | X41: =IFERROR(S41/D41,"") -> 0 | Y41: =Brokerage(F41, L41, G41) -> ERR | Z41: =IF(H41=0,0,CAPITAL!$H$5*Y41) -> 0 | AA41: =IF(I41=0,0,CAPITAL!$H$6*Y41) -> 0 | AB41: =IF(J41=0,0,CAPITAL!$H$7*Y41) -> 0
A42: DIVOPPBEES | B42: 34 | C42: =ENTRY!B36 -> SILVERBEES | D42: =CAPITAL!$C$2 -> 3350000 | E42: =ENTRY!C36 | F42: =ENTRY!D36 | G42: =ENTRY!E36 | H42: =G42*ENTRY!$O36 -> 0 | I42: =G42*ENTRY!$P36 -> 0 | J42: =G42*ENTRY!$Q36 -> 0 | K42: =F42*G42 -> 0 | L42: =ENTRY!F36 | M42: =ENTRY!G36 | N42: =IFERROR(((L42-F42)*G42)/K42,"") | O42: =IFERROR(N42*K42,"") -> 0 | P42: =IFERROR((F42*H42)*N42,"") -> 0 | Q42: =IFERROR((F42*I42)*N42,"") -> 0 | R42: =IFERROR((F42*J42)*N42,"") -> 0 | S42: =IFERROR(O42-Y42,"") | T42: =IFERROR(P42-Z42,"") -> 0 | U42: =IFERROR(Q42-AA42,"") -> 0 | V42: =IFERROR(R42-AB42,"") -> 0 | W42: =IFERROR(S42/K42,"") | X42: =S42/D42 -> 0 | Y42: =Brokerage(F42, L42, G42) -> ERR | Z42: =IF(H42=0,0,CAPITAL!$H$5*Y42) -> 0 | AA42: =IF(I42=0,0,CAPITAL!$H$6*Y42) -> 0 | AB42: =IF(J42=0,0,CAPITAL!$H$7*Y42) -> 0
A43: EVINDIA | B43: 35 | C43: =ENTRY!B37 -> SILVERBEES | D43: =CAPITAL!$C$2 -> 3350000 | E43: =ENTRY!C37 | F43: =ENTRY!D37 | G43: =ENTRY!E37 | H43: =G43*ENTRY!$O37 -> 0 | I43: =G43*ENTRY!$P37 -> 0 | J43: =G43*ENTRY!$Q37 -> 0 | K43: =F43*G43 -> 0 | L43: =ENTRY!F37 | M43: =ENTRY!G37 | N43: =IFERROR(((L43-F43)*G43)/K43,"") | O43: =IFERROR(N43*K43,"") -> 0 | P43: =IFERROR((F43*H43)*N43,"") -> 0 | Q43: =IFERROR((F43*I43)*N43,"") -> 0 | R43: =IFERROR((F43*J43)*N43,"") -> 0 | S43: =IFERROR(O43-Y43,"") | T43: =IFERROR(P43-Z43,"") -> 0 | U43: =IFERROR(Q43-AA43,"") -> 0 | V43: =IFERROR(R43-AB43,"") -> 0 | W43: =IFERROR(S43/K43,"") | X43: =IFERROR(S43/D43,"") -> 0 | Y43: =Brokerage(F43, L43, G43) -> ERR | Z43: =IF(H43=0,0,CAPITAL!$H$5*Y43) -> 0 | AA43: =IF(I43=0,0,CAPITAL!$H$6*Y43) -> 0 | AB43: =IF(J43=0,0,CAPITAL!$H$7*Y43) -> 0
A44: BFSI | B44: 36 | C44: =ENTRY!B38 -> SILVERBEES | D44: =CAPITAL!$C$2 -> 3350000 | E44: =ENTRY!C38 | F44: =ENTRY!D38 | G44: =ENTRY!E38 | H44: =G44*ENTRY!$O38 -> 0 | I44: =G44*ENTRY!$P38 -> 0 | J44: =G44*ENTRY!$Q38 -> 0 | K44: =F44*G44 -> 0 | L44: =ENTRY!F38 | M44: =ENTRY!G38 | N44: =IFERROR(((L44-F44)*G44)/K44,"") | O44: =IFERROR(N44*K44,"") -> 0 | P44: =IFERROR((F44*H44)*N44,"") -> 0 | Q44: =IFERROR((F44*I44)*N44,"") -> 0 | R44: =IFERROR((F44*J44)*N44,"") -> 0 | S44: =IFERROR(O44-Y44,"") | T44: =IFERROR(P44-Z44,"") -> 0 | U44: =IFERROR(Q44-AA44,"") -> 0 | V44: =IFERROR(R44-AB44,"") -> 0 | W44: =IFERROR(S44/K44,"") | X44: =S44/D44 -> 0 | Y44: =Brokerage(F44, L44, G44) -> ERR | Z44: =IF(H44=0,0,CAPITAL!$H$5*Y44) -> 0 | AA44: =IF(I44=0,0,CAPITAL!$H$6*Y44) -> 0 | AB44: =IF(J44=0,0,CAPITAL!$H$7*Y44) -> 0
A45: FMCGIETF | B45: 37 | C45: =ENTRY!B39 -> SILVERBEES | D45: =CAPITAL!$C$2 -> 3350000 | E45: =ENTRY!C39 | F45: =ENTRY!D39 | G45: =ENTRY!E39 | H45: =G45*ENTRY!$O39 -> 0 | I45: =G45*ENTRY!$P39 -> 0 | J45: =G45*ENTRY!$Q39 -> 0 | K45: =F45*G45 -> 0 | L45: =ENTRY!F39 | M45: =ENTRY!G39 | N45: =IFERROR(((L45-F45)*G45)/K45,"") | O45: =IFERROR(N45*K45,"") -> 0 | P45: =IFERROR((F45*H45)*N45,"") -> 0 | Q45: =IFERROR((F45*I45)*N45,"") -> 0 | R45: =IFERROR((F45*J45)*N45,"") -> 0 | S45: =IFERROR(O45-Y45,"") | T45: =IFERROR(P45-Z45,"") -> 0 | U45: =IFERROR(Q45-AA45,"") -> 0 | V45: =IFERROR(R45-AB45,"") -> 0 | W45: =IFERROR(S45/K45,"") | X45: =IFERROR(S45/D45,"") -> 0 | Y45: =Brokerage(F45, L45, G45) -> ERR | Z45: =IF(H45=0,0,CAPITAL!$H$5*Y45) -> 0 | AA45: =IF(I45=0,0,CAPITAL!$H$6*Y45) -> 0 | AB45: =IF(J45=0,0,CAPITAL!$H$7*Y45) -> 0
A46: HEALTHY | B46: 38 | C46: =ENTRY!B40 -> SILVERBEES | D46: =CAPITAL!$C$2 -> 3350000 | E46: =ENTRY!C40 | F46: =ENTRY!D40 | G46: =ENTRY!E40 | H46: =G46*ENTRY!$O40 -> 0 | I46: =G46*ENTRY!$P40 -> 0 | J46: =G46*ENTRY!$Q40 -> 0 | K46: =F46*G46 -> 0 | L46: =ENTRY!F40 | M46: =ENTRY!G40 | N46: =IFERROR(((L46-F46)*G46)/K46,"") | O46: =IFERROR(N46*K46,"") -> 0 | P46: =IFERROR((F46*H46)*N46,"") -> 0 | Q46: =IFERROR((F46*I46)*N46,"") -> 0 | R46: =IFERROR((F46*J46)*N46,"") -> 0 | S46: =IFERROR(O46-Y46,"") | T46: =IFERROR(P46-Z46,"") -> 0 | U46: =IFERROR(Q46-AA46,"") -> 0 | V46: =IFERROR(R46-AB46,"") -> 0 | W46: =IFERROR(S46/K46,"") | X46: =S46/D46 -> 0 | Y46: =Brokerage(F46, L46, G46) -> ERR | Z46: =IF(H46=0,0,CAPITAL!$H$5*Y46) -> 0 | AA46: =IF(I46=0,0,CAPITAL!$H$6*Y46) -> 0 | AB46: =IF(J46=0,0,CAPITAL!$H$7*Y46) -> 0
A47: MOHEALTH | B47: 39 | C47: =ENTRY!B41 -> SILVERBEES | D47: =CAPITAL!$C$2 -> 3350000 | E47: =ENTRY!C41 | F47: =ENTRY!D41 | G47: =ENTRY!E41 | H47: =G47*ENTRY!$O41 -> 0 | I47: =G47*ENTRY!$P41 -> 0 | J47: =G47*ENTRY!$Q41 -> 0 | K47: =F47*G47 -> 0 | L47: =ENTRY!F41 | M47: =ENTRY!G41 | N47: =IFERROR(((L47-F47)*G47)/K47,"") | O47: =IFERROR(N47*K47,"") -> 0 | P47: =IFERROR((F47*H47)*N47,"") -> 0 | Q47: =IFERROR((F47*I47)*N47,"") -> 0 | R47: =IFERROR((F47*J47)*N47,"") -> 0 | S47: =IFERROR(O47-Y47,"") | T47: =IFERROR(P47-Z47,"") -> 0 | U47: =IFERROR(Q47-AA47,"") -> 0 | V47: =IFERROR(R47-AB47,"") -> 0 | W47: =IFERROR(S47/K47,"") | X47: =IFERROR(S47/D47,"") -> 0 | Y47: =Brokerage(F47, L47, G47) -> ERR | Z47: =IF(H47=0,0,CAPITAL!$H$5*Y47) -> 0 | AA47: =IF(I47=0,0,CAPITAL!$H$6*Y47) -> 0 | AB47: =IF(J47=0,0,CAPITAL!$H$7*Y47) -> 0
A48: CONSUMBEES | B48: 40 | C48: =ENTRY!B42 -> SILVERBEES | D48: =CAPITAL!$C$2 -> 3350000 | E48: =ENTRY!C42 | F48: =ENTRY!D42 | G48: =ENTRY!E42 | H48: =G48*ENTRY!$O42 -> 0 | I48: =G48*ENTRY!$P42 -> 0 | J48: =G48*ENTRY!$Q42 -> 0 | K48: =F48*G48 -> 0 | L48: =ENTRY!F42 | M48: =ENTRY!G42 | N48: =IFERROR(((L48-F48)*G48)/K48,"") | O48: =IFERROR(N48*K48,"") -> 0 | P48: =IFERROR((F48*H48)*N48,"") -> 0 | Q48: =IFERROR((F48*I48)*N48,"") -> 0 | R48: =IFERROR((F48*J48)*N48,"") -> 0 | S48: =IFERROR(O48-Y48,"") | T48: =IFERROR(P48-Z48,"") -> 0 | U48: =IFERROR(Q48-AA48,"") -> 0 | V48: =IFERROR(R48-AB48,"") -> 0 | W48: =IFERROR(S48/K48,"") | X48: =S48/D48 -> 0 | Y48: =Brokerage(F48, L48, G48) -> ERR | Z48: =IF(H48=0,0,CAPITAL!$H$5*Y48) -> 0 | AA48: =IF(I48=0,0,CAPITAL!$H$6*Y48) -> 0 | AB48: =IF(J48=0,0,CAPITAL!$H$7*Y48) -> 0
A49: MODEFENCE | B49: 41 | C49: =ENTRY!B43 -> SILVERBEES | D49: =CAPITAL!$C$2 -> 3350000 | E49: =ENTRY!C43 | F49: =ENTRY!D43 | G49: =ENTRY!E43 | H49: =G49*ENTRY!$O43 -> 0 | I49: =G49*ENTRY!$P43 -> 0 | J49: =G49*ENTRY!$Q43 -> 0 | K49: =F49*G49 -> 0 | L49: =ENTRY!F43 | M49: =ENTRY!G43 | N49: =IFERROR(((L49-F49)*G49)/K49,"") | O49: =IFERROR(N49*K49,"") -> 0 | P49: =IFERROR((F49*H49)*N49,"") -> 0 | Q49: =IFERROR((F49*I49)*N49,"") -> 0 | R49: =IFERROR((F49*J49)*N49,"") -> 0 | S49: =IFERROR(O49-Y49,"") | T49: =IFERROR(P49-Z49,"") -> 0 | U49: =IFERROR(Q49-AA49,"") -> 0 | V49: =IFERROR(R49-AB49,"") -> 0 | W49: =IFERROR(S49/K49,"") | X49: =IFERROR(S49/D49,"") -> 0 | Y49: =Brokerage(F49, L49, G49) -> ERR | Z49: =IF(H49=0,0,CAPITAL!$H$5*Y49) -> 0 | AA49: =IF(I49=0,0,CAPITAL!$H$6*Y49) -> 0 | AB49: =IF(J49=0,0,CAPITAL!$H$7*Y49) -> 0
A50: TNIDETF | B50: 42 | C50: =ENTRY!B44 -> SILVERBEES | D50: =CAPITAL!$C$2 -> 3350000 | E50: =ENTRY!C44 | F50: =ENTRY!D44 | G50: =ENTRY!E44 | H50: =G50*ENTRY!$O44 -> 0 | I50: =G50*ENTRY!$P44 -> 0 | J50: =G50*ENTRY!$Q44 -> 0 | K50: =F50*G50 -> 0 | L50: =ENTRY!F44 | M50: =ENTRY!G44 | N50: =IFERROR(((L50-F50)*G50)/K50,"") | O50: =IFERROR(N50*K50,"") -> 0 | P50: =IFERROR((F50*H50)*N50,"") -> 0 | Q50: =IFERROR((F50*I50)*N50,"") -> 0 | R50: =IFERROR((F50*J50)*N50,"") -> 0 | S50: =IFERROR(O50-Y50,"") | T50: =IFERROR(P50-Z50,"") -> 0 | U50: =IFERROR(Q50-AA50,"") -> 0 | V50: =IFERROR(R50-AB50,"") -> 0 | W50: =IFERROR(S50/K50,"") | X50: =S50/D50 -> 0 | Y50: =Brokerage(F50, L50, G50) -> ERR | Z50: =IF(H50=0,0,CAPITAL!$H$5*Y50) -> 0 | AA50: =IF(I50=0,0,CAPITAL!$H$6*Y50) -> 0 | AB50: =IF(J50=0,0,CAPITAL!$H$7*Y50) -> 0
A51: MAKEINDIA | B51: 43 | C51: =ENTRY!B45 -> SILVERBEES | D51: =CAPITAL!$C$2 -> 3350000 | E51: =ENTRY!C45 | F51: =ENTRY!D45 | G51: =ENTRY!E45 | H51: =G51*ENTRY!$O45 -> 0 | I51: =G51*ENTRY!$P45 -> 0 | J51: =G51*ENTRY!$Q45 -> 0 | K51: =F51*G51 -> 0 | L51: =ENTRY!F45 | M51: =ENTRY!G45 | N51: =IFERROR(((L51-F51)*G51)/K51,"") | O51: =IFERROR(N51*K51,"") -> 0 | P51: =IFERROR((F51*H51)*N51,"") -> 0 | Q51: =IFERROR((F51*I51)*N51,"") -> 0 | R51: =IFERROR((F51*J51)*N51,"") -> 0 | S51: =IFERROR(O51-Y51,"") | T51: =IFERROR(P51-Z51,"") -> 0 | U51: =IFERROR(Q51-AA51,"") -> 0 | V51: =IFERROR(R51-AB51,"") -> 0 | W51: =IFERROR(S51/K51,"") | X51: =IFERROR(S51/D51,"") -> 0 | Y51: =Brokerage(F51, L51, G51) -> ERR | Z51: =IF(H51=0,0,CAPITAL!$H$5*Y51) -> 0 | AA51: =IF(I51=0,0,CAPITAL!$H$6*Y51) -> 0 | AB51: =IF(J51=0,0,CAPITAL!$H$7*Y51) -> 0
A52: ITBEES | B52: 44 | C52: =ENTRY!B46 -> SILVERBEES | D52: =CAPITAL!$C$2 -> 3350000 | E52: =ENTRY!C46 | F52: =ENTRY!D46 | G52: =ENTRY!E46 | H52: =G52*ENTRY!$O46 -> 0 | I52: =G52*ENTRY!$P46 -> 0 | J52: =G52*ENTRY!$Q46 -> 0 | K52: =F52*G52 -> 0 | L52: =ENTRY!F46 | M52: =ENTRY!G46 | N52: =IFERROR(((L52-F52)*G52)/K52,"") | O52: =IFERROR(N52*K52,"") -> 0 | P52: =IFERROR((F52*H52)*N52,"") -> 0 | Q52: =IFERROR((F52*I52)*N52,"") -> 0 | R52: =IFERROR((F52*J52)*N52,"") -> 0 | S52: =IFERROR(O52-Y52,"") | T52: =IFERROR(P52-Z52,"") -> 0 | U52: =IFERROR(Q52-AA52,"") -> 0 | V52: =IFERROR(R52-AB52,"") -> 0 | W52: =IFERROR(S52/K52,"") | X52: =S52/D52 -> 0 | Y52: =Brokerage(F52, L52, G52) -> ERR | Z52: =IF(H52=0,0,CAPITAL!$H$5*Y52) -> 0 | AA52: =IF(I52=0,0,CAPITAL!$H$6*Y52) -> 0 | AB52: =IF(J52=0,0,CAPITAL!$H$7*Y52) -> 0
A53: METALIETF | B53: 45 | C53: =ENTRY!B47 -> SILVERBEES | D53: =CAPITAL!$C$2 -> 3350000 | E53: =ENTRY!C47 | F53: =ENTRY!D47 | G53: =ENTRY!E47 | H53: =G53*ENTRY!$O47 -> 0 | I53: =G53*ENTRY!$P47 -> 0 | J53: =G53*ENTRY!$Q47 -> 0 | K53: =F53*G53 -> 0 | L53: =ENTRY!F47 | M53: =ENTRY!G47 | N53: =IFERROR(((L53-F53)*G53)/K53,"") | O53: =IFERROR(N53*K53,"") -> 0 | P53: =IFERROR((F53*H53)*N53,"") -> 0 | Q53: =IFERROR((F53*I53)*N53,"") -> 0 | R53: =IFERROR((F53*J53)*N53,"") -> 0 | S53: =IFERROR(O53-Y53,"") | T53: =IFERROR(P53-Z53,"") -> 0 | U53: =IFERROR(Q53-AA53,"") -> 0 | V53: =IFERROR(R53-AB53,"") -> 0 | W53: =IFERROR(S53/K53,"") | X53: =IFERROR(S53/D53,"") -> 0 | Y53: =Brokerage(F53, L53, G53) -> ERR | Z53: =IF(H53=0,0,CAPITAL!$H$5*Y53) -> 0 | AA53: =IF(I53=0,0,CAPITAL!$H$6*Y53) -> 0 | AB53: =IF(J53=0,0,CAPITAL!$H$7*Y53) -> 0
A54: MOM100 | B54: 46 | C54: =ENTRY!B48 -> SILVERBEES | D54: =CAPITAL!$C$2 -> 3350000 | E54: =ENTRY!C48 | F54: =ENTRY!D48 | G54: =ENTRY!E48 | H54: =G54*ENTRY!$O48 -> 0 | I54: =G54*ENTRY!$P48 -> 0 | J54: =G54*ENTRY!$Q48 -> 0 | K54: =F54*G54 -> 0 | L54: =ENTRY!F48 | M54: =ENTRY!G48 | N54: =IFERROR(((L54-F54)*G54)/K54,"") | O54: =IFERROR(N54*K54,"") -> 0 | P54: =IFERROR((F54*H54)*N54,"") -> 0 | Q54: =IFERROR((F54*I54)*N54,"") -> 0 | R54: =IFERROR((F54*J54)*N54,"") -> 0 | S54: =IFERROR(O54-Y54,"") | T54: =IFERROR(P54-Z54,"") -> 0 | U54: =IFERROR(Q54-AA54,"") -> 0 | V54: =IFERROR(R54-AB54,"") -> 0 | W54: =IFERROR(S54/K54,"") | X54: =S54/D54 -> 0 | Y54: =Brokerage(F54, L54, G54) -> ERR | Z54: =IF(H54=0,0,CAPITAL!$H$5*Y54) -> 0 | AA54: =IF(I54=0,0,CAPITAL!$H$6*Y54) -> 0 | AB54: =IF(J54=0,0,CAPITAL!$H$7*Y54) -> 0
A55: MIDCAPETF | B55: 47 | C55: =ENTRY!B49 -> SILVERBEES | D55: =CAPITAL!$C$2 -> 3350000 | E55: =ENTRY!C49 | F55: =ENTRY!D49 | G55: =ENTRY!E49 | H55: =G55*ENTRY!$O49 -> 0 | I55: =G55*ENTRY!$P49 -> 0 | J55: =G55*ENTRY!$Q49 -> 0 | K55: =F55*G55 -> 0 | L55: =ENTRY!F49 | M55: =ENTRY!G49 | N55: =IFERROR(((L55-F55)*G55)/K55,"") | O55: =IFERROR(N55*K55,"") -> 0 | P55: =IFERROR((F55*H55)*N55,"") -> 0 | Q55: =IFERROR((F55*I55)*N55,"") -> 0 | R55: =IFERROR((F55*J55)*N55,"") -> 0 | S55: =IFERROR(O55-Y55,"") | T55: =IFERROR(P55-Z55,"") -> 0 | U55: =IFERROR(Q55-AA55,"") -> 0 | V55: =IFERROR(R55-AB55,"") -> 0 | W55: =IFERROR(S55/K55,"") | X55: =IFERROR(S55/D55,"") -> 0 | Y55: =Brokerage(F55, L55, G55) -> ERR | Z55: =IF(H55=0,0,CAPITAL!$H$5*Y55) -> 0 | AA55: =IF(I55=0,0,CAPITAL!$H$6*Y55) -> 0 | AB55: =IF(J55=0,0,CAPITAL!$H$7*Y55) -> 0
A56: MIDQ50ADD | B56: 48 | C56: =ENTRY!B50 -> SILVERBEES | D56: =CAPITAL!$C$2 -> 3350000 | E56: =ENTRY!C50 | F56: =ENTRY!D50 | G56: =ENTRY!E50 | H56: =G56*ENTRY!$O50 -> 0 | I56: =G56*ENTRY!$P50 -> 0 | J56: =G56*ENTRY!$Q50 -> 0 | K56: =F56*G56 -> 0 | L56: =ENTRY!F50 | M56: =ENTRY!G50 | N56: =IFERROR(((L56-F56)*G56)/K56,"") | O56: =IFERROR(N56*K56,"") -> 0 | P56: =IFERROR((F56*H56)*N56,"") -> 0 | Q56: =IFERROR((F56*I56)*N56,"") -> 0 | R56: =IFERROR((F56*J56)*N56,"") -> 0 | S56: =IFERROR(O56-Y56,"") | T56: =IFERROR(P56-Z56,"") -> 0 | U56: =IFERROR(Q56-AA56,"") -> 0 | V56: =IFERROR(R56-AB56,"") -> 0 | W56: =IFERROR(S56/K56,"") | X56: =S56/D56 -> 0 | Y56: =Brokerage(F56, L56, G56) -> ERR | Z56: =IF(H56=0,0,CAPITAL!$H$5*Y56) -> 0 | AA56: =IF(I56=0,0,CAPITAL!$H$6*Y56) -> 0 | AB56: =IF(J56=0,0,CAPITAL!$H$7*Y56) -> 0
A57: MIDCAP | B57: 49 | C57: =ENTRY!B51 -> SILVERBEES | D57: =CAPITAL!$C$2 -> 3350000 | E57: =ENTRY!C51 | F57: =ENTRY!D51 | G57: =ENTRY!E51 | H57: =G57*ENTRY!$O51 -> 0 | I57: =G57*ENTRY!$P51 -> 0 | J57: =G57*ENTRY!$Q51 -> 0 | K57: =F57*G57 -> 0 | L57: =ENTRY!F51 | M57: =ENTRY!G51 | N57: =IFERROR(((L57-F57)*G57)/K57,"") | O57: =IFERROR(N57*K57,"") -> 0 | P57: =IFERROR((F57*H57)*N57,"") -> 0 | Q57: =IFERROR((F57*I57)*N57,"") -> 0 | R57: =IFERROR((F57*J57)*N57,"") -> 0 | S57: =IFERROR(O57-Y57,"") | T57: =IFERROR(P57-Z57,"") -> 0 | U57: =IFERROR(Q57-AA57,"") -> 0 | V57: =IFERROR(R57-AB57,"") -> 0 | W57: =IFERROR(S57/K57,"") | X57: =IFERROR(S57/D57,"") -> 0 | Y57: =Brokerage(F57, L57, G57) -> ERR | Z57: =IF(H57=0,0,CAPITAL!$H$5*Y57) -> 0 | AA57: =IF(I57=0,0,CAPITAL!$H$6*Y57) -> 0 | AB57: =IF(J57=0,0,CAPITAL!$H$7*Y57) -> 0
A58: NEXT50IETF | B58: 50 | C58: =ENTRY!B52 -> SILVERBEES | D58: =CAPITAL!$C$2 -> 3350000 | E58: =ENTRY!C52 | F58: =ENTRY!D52 | G58: =ENTRY!E52 | H58: =G58*ENTRY!$O52 -> 0 | I58: =G58*ENTRY!$P52 -> 0 | J58: =G58*ENTRY!$Q52 -> 0 | K58: =F58*G58 -> 0 | L58: =ENTRY!F52 | M58: =ENTRY!G52 | N58: =IFERROR(((L58-F58)*G58)/K58,"") | O58: =IFERROR(N58*K58,"") -> 0 | P58: =IFERROR((F58*H58)*N58,"") -> 0 | Q58: =IFERROR((F58*I58)*N58,"") -> 0 | R58: =IFERROR((F58*J58)*N58,"") -> 0 | S58: =IFERROR(O58-Y58,"") | T58: =IFERROR(P58-Z58,"") -> 0 | U58: =IFERROR(Q58-AA58,"") -> 0 | V58: =IFERROR(R58-AB58,"") -> 0 | W58: =IFERROR(S58/K58,"") | X58: =S58/D58 -> 0 | Y58: =Brokerage(F58, L58, G58) -> ERR | Z58: =IF(H58=0,0,CAPITAL!$H$5*Y58) -> 0 | AA58: =IF(I58=0,0,CAPITAL!$H$6*Y58) -> 0 | AB58: =IF(J58=0,0,CAPITAL!$H$7*Y58) -> 0
A59: OILIETF | B59: 51 | C59: =ENTRY!B53 -> SILVERBEES | D59: =CAPITAL!$C$2 -> 3350000 | E59: =ENTRY!C53 | F59: =ENTRY!D53 | G59: =ENTRY!E53 | H59: =G59*ENTRY!$O53 -> 0 | I59: =G59*ENTRY!$P53 -> 0 | J59: =G59*ENTRY!$Q53 -> 0 | K59: =F59*G59 -> 0 | L59: =ENTRY!F53 | M59: =ENTRY!G53 | N59: =IFERROR(((L59-F59)*G59)/K59,"") | O59: =IFERROR(N59*K59,"") -> 0 | P59: =IFERROR((F59*H59)*N59,"") -> 0 | Q59: =IFERROR((F59*I59)*N59,"") -> 0 | R59: =IFERROR((F59*J59)*N59,"") -> 0 | S59: =IFERROR(O59-Y59,"") | T59: =IFERROR(P59-Z59,"") -> 0 | U59: =IFERROR(Q59-AA59,"") -> 0 | V59: =IFERROR(R59-AB59,"") -> 0 | W59: =IFERROR(S59/K59,"") | X59: =IFERROR(S59/D59,"") -> 0 | Y59: =Brokerage(F59, L59, G59) -> ERR | Z59: =IF(H59=0,0,CAPITAL!$H$5*Y59) -> 0 | AA59: =IF(I59=0,0,CAPITAL!$H$6*Y59) -> 0 | AB59: =IF(J59=0,0,CAPITAL!$H$7*Y59) -> 0
A60: PHARMABEES | B60: 52 | C60: =ENTRY!B54 -> SILVERBEES | D60: =CAPITAL!$C$2 -> 3350000 | E60: =ENTRY!C54 | F60: =ENTRY!D54 | G60: =ENTRY!E54 | H60: =G60*ENTRY!$O54 -> 0 | I60: =G60*ENTRY!$P54 -> 0 | J60: =G60*ENTRY!$Q54 -> 0 | K60: =F60*G60 -> 0 | L60: =ENTRY!F54 | M60: =ENTRY!G54 | N60: =IFERROR(((L60-F60)*G60)/K60,"") | O60: =IFERROR(N60*K60,"") -> 0 | P60: =IFERROR((F60*H60)*N60,"") -> 0 | Q60: =IFERROR((F60*I60)*N60,"") -> 0 | R60: =IFERROR((F60*J60)*N60,"") -> 0 | S60: =IFERROR(O60-Y60,"") | T60: =IFERROR(P60-Z60,"") -> 0 | U60: =IFERROR(Q60-AA60,"") -> 0 | V60: =IFERROR(R60-AB60,"") -> 0 | W60: =IFERROR(S60/K60,"") | X60: =S60/D60 -> 0 | Y60: =Brokerage(F60, L60, G60) -> ERR | Z60: =IF(H60=0,0,CAPITAL!$H$5*Y60) -> 0 | AA60: =IF(I60=0,0,CAPITAL!$H$6*Y60) -> 0 | AB60: =IF(J60=0,0,CAPITAL!$H$7*Y60) -> 0
A61: PVTBANIETF | B61: 53 | C61: =ENTRY!B55 -> SILVERBEES | D61: =CAPITAL!$C$2 -> 3350000 | E61: =ENTRY!C55 | F61: =ENTRY!D55 | G61: =ENTRY!E55 | H61: =G61*ENTRY!$O55 -> 0 | I61: =G61*ENTRY!$P55 -> 0 | J61: =G61*ENTRY!$Q55 -> 0 | K61: =F61*G61 -> 0 | L61: =ENTRY!F55 | M61: =ENTRY!G55 | N61: =IFERROR(((L61-F61)*G61)/K61,"") | O61: =IFERROR(N61*K61,"") -> 0 | P61: =IFERROR((F61*H61)*N61,"") -> 0 | Q61: =IFERROR((F61*I61)*N61,"") -> 0 | R61: =IFERROR((F61*J61)*N61,"") -> 0 | S61: =IFERROR(O61-Y61,"") | T61: =IFERROR(P61-Z61,"") -> 0 | U61: =IFERROR(Q61-AA61,"") -> 0 | V61: =IFERROR(R61-AB61,"") -> 0 | W61: =IFERROR(S61/K61,"") | X61: =IFERROR(S61/D61,"") -> 0 | Y61: =Brokerage(F61, L61, G61) -> ERR | Z61: =IF(H61=0,0,CAPITAL!$H$5*Y61) -> 0 | AA61: =IF(I61=0,0,CAPITAL!$H$6*Y61) -> 0 | AB61: =IF(J61=0,0,CAPITAL!$H$7*Y61) -> 0
A62: PSUBNKBEES | B62: 54 | C62: =ENTRY!B56 -> SILVERBEES | D62: =CAPITAL!$C$2 -> 3350000 | E62: =ENTRY!C56 | F62: =ENTRY!D56 | G62: =ENTRY!E56 | H62: =G62*ENTRY!$O56 -> 0 | I62: =G62*ENTRY!$P56 -> 0 | J62: =G62*ENTRY!$Q56 -> 0 | K62: =F62*G62 -> 0 | L62: =ENTRY!F56 | M62: =ENTRY!G56 | N62: =IFERROR(((L62-F62)*G62)/K62,"") | O62: =IFERROR(N62*K62,"") -> 0 | P62: =IFERROR((F62*H62)*N62,"") -> 0 | Q62: =IFERROR((F62*I62)*N62,"") -> 0 | R62: =IFERROR((F62*J62)*N62,"") -> 0 | S62: =IFERROR(O62-Y62,"") | T62: =IFERROR(P62-Z62,"") -> 0 | U62: =IFERROR(Q62-AA62,"") -> 0 | V62: =IFERROR(R62-AB62,"") -> 0 | W62: =IFERROR(S62/K62,"") | X62: =S62/D62 -> 0 | Y62: =Brokerage(F62, L62, G62) -> ERR | Z62: =IF(H62=0,0,CAPITAL!$H$5*Y62) -> 0 | AA62: =IF(I62=0,0,CAPITAL!$H$6*Y62) -> 0 | AB62: =IF(J62=0,0,CAPITAL!$H$7*Y62) -> 0
A63: TOP10ADD | B63: 55 | C63: =ENTRY!B57 -> SILVERBEES | D63: =CAPITAL!$C$2 -> 3350000 | E63: =ENTRY!C57 | F63: =ENTRY!D57 | G63: =ENTRY!E57 | H63: =G63*ENTRY!$O57 -> 0 | I63: =G63*ENTRY!$P57 -> 0 | J63: =G63*ENTRY!$Q57 -> 0 | K63: =F63*G63 -> 0 | L63: =ENTRY!F57 | M63: =ENTRY!G57 | N63: =IFERROR(((L63-F63)*G63)/K63,"") | O63: =IFERROR(N63*K63,"") -> 0 | P63: =IFERROR((F63*H63)*N63,"") -> 0 | Q63: =IFERROR((F63*I63)*N63,"") -> 0 | R63: =IFERROR((F63*J63)*N63,"") -> 0 | S63: =IFERROR(O63-Y63,"") | T63: =IFERROR(P63-Z63,"") -> 0 | U63: =IFERROR(Q63-AA63,"") -> 0 | V63: =IFERROR(R63-AB63,"") -> 0 | W63: =IFERROR(S63/K63,"") | X63: =IFERROR(S63/D63,"") -> 0 | Y63: =Brokerage(F63, L63, G63) -> ERR | Z63: =IF(H63=0,0,CAPITAL!$H$5*Y63) -> 0 | AA63: =IF(I63=0,0,CAPITAL!$H$6*Y63) -> 0 | AB63: =IF(J63=0,0,CAPITAL!$H$7*Y63) -> 0
A64: ESG | B64: 56 | C64: =ENTRY!B58 -> SILVERBEES | D64: =CAPITAL!$C$2 -> 3350000 | E64: =ENTRY!C58 | F64: =ENTRY!D58 | G64: =ENTRY!E58 | H64: =G64*ENTRY!$O58 -> 0 | I64: =G64*ENTRY!$P58 -> 0 | J64: =G64*ENTRY!$Q58 -> 0 | K64: =F64*G64 -> 0 | L64: =ENTRY!F58 | M64: =ENTRY!G58 | N64: =IFERROR(((L64-F64)*G64)/K64,"") | O64: =IFERROR(N64*K64,"") -> 0 | P64: =IFERROR((F64*H64)*N64,"") -> 0 | Q64: =IFERROR((F64*I64)*N64,"") -> 0 | R64: =IFERROR((F64*J64)*N64,"") -> 0 | S64: =IFERROR(O64-Y64,"") | T64: =IFERROR(P64-Z64,"") -> 0 | U64: =IFERROR(Q64-AA64,"") -> 0 | V64: =IFERROR(R64-AB64,"") -> 0 | W64: =IFERROR(S64/K64,"") | X64: =S64/D64 -> 0 | Y64: =Brokerage(F64, L64, G64) -> ERR | Z64: =IF(H64=0,0,CAPITAL!$H$5*Y64) -> 0 | AA64: =IF(I64=0,0,CAPITAL!$H$6*Y64) -> 0 | AB64: =IF(J64=0,0,CAPITAL!$H$7*Y64) -> 0
A65: NV20IETF | B65: 57 | C65: =ENTRY!B59 -> SILVERBEES | D65: =CAPITAL!$C$2 -> 3350000 | E65: =ENTRY!C59 | F65: =ENTRY!D59 | G65: =ENTRY!E59 | H65: =G65*ENTRY!$O59 -> 0 | I65: =G65*ENTRY!$P59 -> 0 | J65: =G65*ENTRY!$Q59 -> 0 | K65: =F65*G65 -> 0 | L65: =ENTRY!F59 | M65: =ENTRY!G59 | N65: =IFERROR(((L65-F65)*G65)/K65,"") | O65: =IFERROR(N65*K65,"") -> 0 | P65: =IFERROR((F65*H65)*N65,"") -> 0 | Q65: =IFERROR((F65*I65)*N65,"") -> 0 | R65: =IFERROR((F65*J65)*N65,"") -> 0 | S65: =IFERROR(O65-Y65,"") | T65: =IFERROR(P65-Z65,"") -> 0 | U65: =IFERROR(Q65-AA65,"") -> 0 | V65: =IFERROR(R65-AB65,"") -> 0 | W65: =IFERROR(S65/K65,"") | X65: =IFERROR(S65/D65,"") -> 0 | Y65: =Brokerage(F65, L65, G65) -> ERR | Z65: =IF(H65=0,0,CAPITAL!$H$5*Y65) -> 0 | AA65: =IF(I65=0,0,CAPITAL!$H$6*Y65) -> 0 | AB65: =IF(J65=0,0,CAPITAL!$H$7*Y65) -> 0
A66: MULTICAP | B66: 58 | C66: =ENTRY!B60 -> SILVERBEES | D66: =CAPITAL!$C$2 -> 3350000 | E66: =ENTRY!C60 | F66: =ENTRY!D60 | G66: =ENTRY!E60 | H66: =G66*ENTRY!$O60 -> 0 | I66: =G66*ENTRY!$P60 -> 0 | J66: =G66*ENTRY!$Q60 -> 0 | K66: =F66*G66 -> 0 | L66: =ENTRY!F60 | M66: =ENTRY!G60 | N66: =IFERROR(((L66-F66)*G66)/K66,"") | O66: =IFERROR(N66*K66,"") -> 0 | P66: =IFERROR((F66*H66)*N66,"") -> 0 | Q66: =IFERROR((F66*I66)*N66,"") -> 0 | R66: =IFERROR((F66*J66)*N66,"") -> 0 | S66: =IFERROR(O66-Y66,"") | T66: =IFERROR(P66-Z66,"") -> 0 | U66: =IFERROR(Q66-AA66,"") -> 0 | V66: =IFERROR(R66-AB66,"") -> 0 | W66: =IFERROR(S66/K66,"") | X66: =S66/D66 -> 0 | Y66: =Brokerage(F66, L66, G66) -> ERR | Z66: =IF(H66=0,0,CAPITAL!$H$5*Y66) -> 0 | AA66: =IF(I66=0,0,CAPITAL!$H$6*Y66) -> 0 | AB66: =IF(J66=0,0,CAPITAL!$H$7*Y66) -> 0
A67: EMULTIMQ | B67: 59 | C67: =ENTRY!B61 -> SILVERBEES | D67: =CAPITAL!$C$2 -> 3350000 | E67: =ENTRY!C61 | F67: =ENTRY!D61 | G67: =ENTRY!E61 | H67: =G67*ENTRY!$O61 -> 0 | I67: =G67*ENTRY!$P61 -> 0 | J67: =G67*ENTRY!$Q61 -> 0 | K67: =F67*G67 -> 0 | L67: =ENTRY!F61 | M67: =ENTRY!G61 | N67: =IFERROR(((L67-F67)*G67)/K67,"") | O67: =IFERROR(N67*K67,"") -> 0 | P67: =IFERROR((F67*H67)*N67,"") -> 0 | Q67: =IFERROR((F67*I67)*N67,"") -> 0 | R67: =IFERROR((F67*J67)*N67,"") -> 0 | S67: =IFERROR(O67-Y67,"") | T67: =IFERROR(P67-Z67,"") -> 0 | U67: =IFERROR(Q67-AA67,"") -> 0 | V67: =IFERROR(R67-AB67,"") -> 0 | W67: =IFERROR(S67/K67,"") | X67: =IFERROR(S67/D67,"") -> 0 | Y67: =Brokerage(F67, L67, G67) -> ERR | Z67: =IF(H67=0,0,CAPITAL!$H$5*Y67) -> 0 | AA67: =IF(I67=0,0,CAPITAL!$H$6*Y67) -> 0 | AB67: =IF(J67=0,0,CAPITAL!$H$7*Y67) -> 0
A68: MAFANG | B68: 60 | C68: =ENTRY!B62 -> SILVERBEES | D68: =CAPITAL!$C$2 -> 3350000 | E68: =ENTRY!C62 | F68: =ENTRY!D62 | G68: =ENTRY!E62 | H68: =G68*ENTRY!$O62 -> 0 | I68: =G68*ENTRY!$P62 -> 0 | J68: =G68*ENTRY!$Q62 -> 0 | K68: =F68*G68 -> 0 | L68: =ENTRY!F62 | M68: =ENTRY!G62 | N68: =IFERROR(((L68-F68)*G68)/K68,"") | O68: =IFERROR(N68*K68,"") -> 0 | P68: =IFERROR((F68*H68)*N68,"") -> 0 | Q68: =IFERROR((F68*I68)*N68,"") -> 0 | R68: =IFERROR((F68*J68)*N68,"") -> 0 | S68: =IFERROR(O68-Y68,"") | T68: =IFERROR(P68-Z68,"") -> 0 | U68: =IFERROR(Q68-AA68,"") -> 0 | V68: =IFERROR(R68-AB68,"") -> 0 | W68: =IFERROR(S68/K68,"") | X68: =S68/D68 -> 0 | Y68: =Brokerage(F68, L68, G68) -> ERR | Z68: =IF(H68=0,0,CAPITAL!$H$5*Y68) -> 0 | AA68: =IF(I68=0,0,CAPITAL!$H$6*Y68) -> 0 | AB68: =IF(J68=0,0,CAPITAL!$H$7*Y68) -> 0
A69: MASPTOP50 | B69: 61 | C69: =ENTRY!B63 -> SILVERBEES | D69: =CAPITAL!$C$2 -> 3350000 | E69: =ENTRY!C63 | F69: =ENTRY!D63 | G69: =ENTRY!E63 | H69: =G69*ENTRY!$O63 -> 0 | I69: =G69*ENTRY!$P63 -> 0 | J69: =G69*ENTRY!$Q63 -> 0 | K69: =F69*G69 -> 0 | L69: =ENTRY!F63 | M69: =ENTRY!G63 | N69: =IFERROR(((L69-F69)*G69)/K69,"") | O69: =IFERROR(N69*K69,"") -> 0 | P69: =IFERROR((F69*H69)*N69,"") -> 0 | Q69: =IFERROR((F69*I69)*N69,"") -> 0 | R69: =IFERROR((F69*J69)*N69,"") -> 0 | S69: =IFERROR(O69-Y69,"") | T69: =IFERROR(P69-Z69,"") -> 0 | U69: =IFERROR(Q69-AA69,"") -> 0 | V69: =IFERROR(R69-AB69,"") -> 0 | W69: =IFERROR(S69/K69,"") | X69: =IFERROR(S69/D69,"") -> 0 | Y69: =Brokerage(F69, L69, G69) -> ERR | Z69: =IF(H69=0,0,CAPITAL!$H$5*Y69) -> 0 | AA69: =IF(I69=0,0,CAPITAL!$H$6*Y69) -> 0 | AB69: =IF(J69=0,0,CAPITAL!$H$7*Y69) -> 0
A70: ICICIB22 | B70: 62 | C70: =ENTRY!B64 -> SILVERBEES | D70: =CAPITAL!$C$2 -> 3350000 | E70: =ENTRY!C64 | F70: =ENTRY!D64 | G70: =ENTRY!E64 | H70: =G70*ENTRY!$O64 -> 0 | I70: =G70*ENTRY!$P64 -> 0 | J70: =G70*ENTRY!$Q64 -> 0 | K70: =F70*G70 -> 0 | L70: =ENTRY!F64 | M70: =ENTRY!G64 | N70: =IFERROR(((L70-F70)*G70)/K70,"") | O70: =IFERROR(N70*K70,"") -> 0 | P70: =IFERROR((F70*H70)*N70,"") -> 0 | Q70: =IFERROR((F70*I70)*N70,"") -> 0 | R70: =IFERROR((F70*J70)*N70,"") -> 0 | S70: =IFERROR(O70-Y70,"") | T70: =IFERROR(P70-Z70,"") -> 0 | U70: =IFERROR(Q70-AA70,"") -> 0 | V70: =IFERROR(R70-AB70,"") -> 0 | W70: =IFERROR(S70/K70,"") | X70: =S70/D70 -> 0 | Y70: =Brokerage(F70, L70, G70) -> ERR | Z70: =IF(H70=0,0,CAPITAL!$H$5*Y70) -> 0 | AA70: =IF(I70=0,0,CAPITAL!$H$6*Y70) -> 0 | AB70: =IF(J70=0,0,CAPITAL!$H$7*Y70) -> 0
A71: MIDSELIETF | B71: 63 | C71: =ENTRY!B65 -> SILVERBEES | D71: =CAPITAL!$C$2 -> 3350000 | E71: =ENTRY!C65 | F71: =ENTRY!D65 | G71: =ENTRY!E65 | H71: =G71*ENTRY!$O65 -> 0 | I71: =G71*ENTRY!$P65 -> 0 | J71: =G71*ENTRY!$Q65 -> 0 | K71: =F71*G71 -> 0 | L71: =ENTRY!F65 | M71: =ENTRY!G65 | N71: =IFERROR(((L71-F71)*G71)/K71,"") | O71: =IFERROR(N71*K71,"") -> 0 | P71: =IFERROR((F71*H71)*N71,"") -> 0 | Q71: =IFERROR((F71*I71)*N71,"") -> 0 | R71: =IFERROR((F71*J71)*N71,"") -> 0 | S71: =IFERROR(O71-Y71,"") | T71: =IFERROR(P71-Z71,"") -> 0 | U71: =IFERROR(Q71-AA71,"") -> 0 | V71: =IFERROR(R71-AB71,"") -> 0 | W71: =IFERROR(S71/K71,"") | X71: =IFERROR(S71/D71,"") -> 0 | Y71: =Brokerage(F71, L71, G71) -> ERR | Z71: =IF(H71=0,0,CAPITAL!$H$5*Y71) -> 0 | AA71: =IF(I71=0,0,CAPITAL!$H$6*Y71) -> 0 | AB71: =IF(J71=0,0,CAPITAL!$H$7*Y71) -> 0
A72: SILVERBEES | B72: 64 | C72: =ENTRY!B66 -> SILVERBEES | D72: =CAPITAL!$C$2 -> 3350000 | E72: =ENTRY!C66 | F72: =ENTRY!D66 | G72: =ENTRY!E66 | H72: =G72*ENTRY!$O66 -> 0 | I72: =G72*ENTRY!$P66 -> 0 | J72: =G72*ENTRY!$Q66 -> 0 | K72: =F72*G72 -> 0 | L72: =ENTRY!F66 | M72: =ENTRY!G66 | N72: =IFERROR(((L72-F72)*G72)/K72,"") | O72: =IFERROR(N72*K72,"") -> 0 | P72: =IFERROR((F72*H72)*N72,"") -> 0 | Q72: =IFERROR((F72*I72)*N72,"") -> 0 | R72: =IFERROR((F72*J72)*N72,"") -> 0 | S72: =IFERROR(O72-Y72,"") | T72: =IFERROR(P72-Z72,"") -> 0 | U72: =IFERROR(Q72-AA72,"") -> 0 | V72: =IFERROR(R72-AB72,"") -> 0 | W72: =IFERROR(S72/K72,"") | X72: =S72/D72 -> 0 | Y72: =Brokerage(F72, L72, G72) -> ERR | Z72: =IF(H72=0,0,CAPITAL!$H$5*Y72) -> 0 | AA72: =IF(I72=0,0,CAPITAL!$H$6*Y72) -> 0 | AB72: =IF(J72=0,0,CAPITAL!$H$7*Y72) -> 0
A73: SENSEXIETF | B73: 65 | C73: =ENTRY!B67 -> SILVERBEES | D73: =CAPITAL!$C$2 -> 3350000 | E73: =ENTRY!C67 | F73: =ENTRY!D67 | G73: =ENTRY!E67 | H73: =G73*ENTRY!$O67 -> 0 | I73: =G73*ENTRY!$P67 -> 0 | J73: =G73*ENTRY!$Q67 -> 0 | K73: =F73*G73 -> 0 | L73: =ENTRY!F67 | M73: =ENTRY!G67 | N73: =IFERROR(((L73-F73)*G73)/K73,"") | O73: =IFERROR(N73*K73,"") -> 0 | P73: =IFERROR((F73*H73)*N73,"") -> 0 | Q73: =IFERROR((F73*I73)*N73,"") -> 0 | R73: =IFERROR((F73*J73)*N73,"") -> 0 | S73: =IFERROR(O73-Y73,"") | T73: =IFERROR(P73-Z73,"") -> 0 | U73: =IFERROR(Q73-AA73,"") -> 0 | V73: =IFERROR(R73-AB73,"") -> 0 | W73: =IFERROR(S73/K73,"") | X73: =IFERROR(S73/D73,"") -> 0 | Y73: =Brokerage(F73, L73, G73) -> ERR | Z73: =IF(H73=0,0,CAPITAL!$H$5*Y73) -> 0 | AA73: =IF(I73=0,0,CAPITAL!$H$6*Y73) -> 0 | AB73: =IF(J73=0,0,CAPITAL!$H$7*Y73) -> 0
A74: SHARIABEES | B74: 66 | C74: =ENTRY!B68 -> SILVERBEES | D74: =CAPITAL!$C$2 -> 3350000 | E74: =ENTRY!C68 | F74: =ENTRY!D68 | G74: =ENTRY!E68 | H74: =G74*ENTRY!$O68 -> 0 | I74: =G74*ENTRY!$P68 -> 0 | J74: =G74*ENTRY!$Q68 -> 0 | K74: =F74*G74 -> 0 | L74: =ENTRY!F68 | M74: =ENTRY!G68 | N74: =IFERROR(((L74-F74)*G74)/K74,"") | O74: =IFERROR(N74*K74,"") -> 0 | P74: =IFERROR((F74*H74)*N74,"") -> 0 | Q74: =IFERROR((F74*I74)*N74,"") -> 0 | R74: =IFERROR((F74*J74)*N74,"") -> 0 | S74: =IFERROR(O74-Y74,"") | T74: =IFERROR(P74-Z74,"") -> 0 | U74: =IFERROR(Q74-AA74,"") -> 0 | V74: =IFERROR(R74-AB74,"") -> 0 | W74: =IFERROR(S74/K74,"") | X74: =S74/D74 -> 0 | Y74: =Brokerage(F74, L74, G74) -> ERR | Z74: =IF(H74=0,0,CAPITAL!$H$5*Y74) -> 0 | AA74: =IF(I74=0,0,CAPITAL!$H$6*Y74) -> 0 | AB74: =IF(J74=0,0,CAPITAL!$H$7*Y74) -> 0
A75: ITBEES | B75: 67 | C75: =ENTRY!B69 -> SILVERBEES | D75: =CAPITAL!$C$2 -> 3350000 | E75: =ENTRY!C69 | F75: =ENTRY!D69 | G75: =ENTRY!E69 | H75: =G75*ENTRY!$O69 -> 0 | I75: =G75*ENTRY!$P69 -> 0 | J75: =G75*ENTRY!$Q69 -> 0 | K75: =F75*G75 -> 0 | L75: =ENTRY!F69 | M75: =ENTRY!G69 | N75: =IFERROR(((L75-F75)*G75)/K75,"") | O75: =IFERROR(N75*K75,"") -> 0 | P75: =IFERROR((F75*H75)*N75,"") -> 0 | Q75: =IFERROR((F75*I75)*N75,"") -> 0 | R75: =IFERROR((F75*J75)*N75,"") -> 0 | S75: =IFERROR(O75-Y75,"") | T75: =IFERROR(P75-Z75,"") -> 0 | U75: =IFERROR(Q75-AA75,"") -> 0 | V75: =IFERROR(R75-AB75,"") -> 0 | W75: =IFERROR(S75/K75,"") | X75: =IFERROR(S75/D75,"") -> 0 | Y75: =Brokerage(F75, L75, G75) -> ERR | Z75: =IF(H75=0,0,CAPITAL!$H$5*Y75) -> 0 | AA75: =IF(I75=0,0,CAPITAL!$H$6*Y75) -> 0 | AB75: =IF(J75=0,0,CAPITAL!$H$7*Y75) -> 0
A76: GOLDBEES | B76: 68 | C76: =ENTRY!B70 -> SILVERBEES | D76: =CAPITAL!$C$2 -> 3350000 | E76: =ENTRY!C70 | F76: =ENTRY!D70 | G76: =ENTRY!E70 | H76: =G76*ENTRY!$O70 -> 0 | I76: =G76*ENTRY!$P70 -> 0 | J76: =G76*ENTRY!$Q70 -> 0 | K76: =F76*G76 -> 0 | L76: =ENTRY!F70 | M76: =ENTRY!G70 | N76: =IFERROR(((L76-F76)*G76)/K76,"") | O76: =IFERROR(N76*K76,"") -> 0 | P76: =IFERROR((F76*H76)*N76,"") -> 0 | Q76: =IFERROR((F76*I76)*N76,"") -> 0 | R76: =IFERROR((F76*J76)*N76,"") -> 0 | S76: =IFERROR(O76-Y76,"") | T76: =IFERROR(P76-Z76,"") -> 0 | U76: =IFERROR(Q76-AA76,"") -> 0 | V76: =IFERROR(R76-AB76,"") -> 0 | W76: =IFERROR(S76/K76,"") | X76: =S76/D76 -> 0 | Y76: =Brokerage(F76, L76, G76) -> ERR | Z76: =IF(H76=0,0,CAPITAL!$H$5*Y76) -> 0 | AA76: =IF(I76=0,0,CAPITAL!$H$6*Y76) -> 0 | AB76: =IF(J76=0,0,CAPITAL!$H$7*Y76) -> 0
A77: JUNIORBEES | B77: 69 | C77: =ENTRY!B71 -> SILVERBEES | D77: =CAPITAL!$C$2 -> 3350000 | E77: =ENTRY!C71 | F77: =ENTRY!D71 | G77: =ENTRY!E71 | H77: =G77*ENTRY!$O71 -> 0 | I77: =G77*ENTRY!$P71 -> 0 | J77: =G77*ENTRY!$Q71 -> 0 | K77: =F77*G77 -> 0 | L77: =ENTRY!F71 | M77: =ENTRY!G71 | N77: =IFERROR(((L77-F77)*G77)/K77,"") | O77: =IFERROR(N77*K77,"") -> 0 | P77: =IFERROR((F77*H77)*N77,"") -> 0 | Q77: =IFERROR((F77*I77)*N77,"") -> 0 | R77: =IFERROR((F77*J77)*N77,"") -> 0 | S77: =IFERROR(O77-Y77,"") | T77: =IFERROR(P77-Z77,"") -> 0 | U77: =IFERROR(Q77-AA77,"") -> 0 | V77: =IFERROR(R77-AB77,"") -> 0 | W77: =IFERROR(S77/K77,"") | X77: =IFERROR(S77/D77,"") -> 0 | Y77: =Brokerage(F77, L77, G77) -> ERR | Z77: =IF(H77=0,0,CAPITAL!$H$5*Y77) -> 0 | AA77: =IF(I77=0,0,CAPITAL!$H$6*Y77) -> 0 | AB77: =IF(J77=0,0,CAPITAL!$H$7*Y77) -> 0
A78: BANKBEES | B78: 70 | C78: =ENTRY!B72 -> SILVERBEES | D78: =CAPITAL!$C$2 -> 3350000 | E78: =ENTRY!C72 | F78: =ENTRY!D72 | G78: =ENTRY!E72 | H78: =G78*ENTRY!$O72 -> 0 | I78: =G78*ENTRY!$P72 -> 0 | J78: =G78*ENTRY!$Q72 -> 0 | K78: =F78*G78 -> 0 | L78: =ENTRY!F72 | M78: =ENTRY!G72 | N78: =IFERROR(((L78-F78)*G78)/K78,"") | O78: =IFERROR(N78*K78,"") -> 0 | P78: =IFERROR((F78*H78)*N78,"") -> 0 | Q78: =IFERROR((F78*I78)*N78,"") -> 0 | R78: =IFERROR((F78*J78)*N78,"") -> 0 | S78: =IFERROR(O78-Y78,"") | T78: =IFERROR(P78-Z78,"") -> 0 | U78: =IFERROR(Q78-AA78,"") -> 0 | V78: =IFERROR(R78-AB78,"") -> 0 | W78: =IFERROR(S78/K78,"") | X78: =S78/D78 -> 0 | Y78: =Brokerage(F78, L78, G78) -> ERR | Z78: =IF(H78=0,0,CAPITAL!$H$5*Y78) -> 0 | AA78: =IF(I78=0,0,CAPITAL!$H$6*Y78) -> 0 | AB78: =IF(J78=0,0,CAPITAL!$H$7*Y78) -> 0
A79: NIFTYBEES | B79: 71 | C79: =ENTRY!B73 -> SILVERBEES | D79: =CAPITAL!$C$2 -> 3350000 | E79: =ENTRY!C73 | F79: =ENTRY!D73 | G79: =ENTRY!E73 | H79: =G79*ENTRY!$O73 -> 0 | I79: =G79*ENTRY!$P73 -> 0 | J79: =G79*ENTRY!$Q73 -> 0 | K79: =F79*G79 -> 0 | L79: =ENTRY!F73 | M79: =ENTRY!G73 | N79: =IFERROR(((L79-F79)*G79)/K79,"") | O79: =IFERROR(N79*K79,"") -> 0 | P79: =IFERROR((F79*H79)*N79,"") -> 0 | Q79: =IFERROR((F79*I79)*N79,"") -> 0 | R79: =IFERROR((F79*J79)*N79,"") -> 0 | S79: =IFERROR(O79-Y79,"") | T79: =IFERROR(P79-Z79,"") -> 0 | U79: =IFERROR(Q79-AA79,"") -> 0 | V79: =IFERROR(R79-AB79,"") -> 0 | W79: =IFERROR(S79/K79,"") | X79: =IFERROR(S79/D79,"") -> 0 | Y79: =Brokerage(F79, L79, G79) -> ERR | Z79: =IF(H79=0,0,CAPITAL!$H$5*Y79) -> 0 | AA79: =IF(I79=0,0,CAPITAL!$H$6*Y79) -> 0 | AB79: =IF(J79=0,0,CAPITAL!$H$7*Y79) -> 0
A80: AUTOBEES | B80: 72 | C80: =ENTRY!B74 -> SILVERBEES | D80: =CAPITAL!$C$2 -> 3350000 | E80: =ENTRY!C74 | F80: =ENTRY!D74 | G80: =ENTRY!E74 | H80: =G80*ENTRY!$O74 -> 0 | I80: =G80*ENTRY!$P74 -> 0 | J80: =G80*ENTRY!$Q74 -> 0 | K80: =F80*G80 -> 0 | L80: =ENTRY!F74 | M80: =ENTRY!G74 | N80: =IFERROR(((L80-F80)*G80)/K80,"") | O80: =IFERROR(N80*K80,"") -> 0 | P80: =IFERROR((F80*H80)*N80,"") -> 0 | Q80: =IFERROR((F80*I80)*N80,"") -> 0 | R80: =IFERROR((F80*J80)*N80,"") -> 0 | S80: =IFERROR(O80-Y80,"") | T80: =IFERROR(P80-Z80,"") -> 0 | U80: =IFERROR(Q80-AA80,"") -> 0 | V80: =IFERROR(R80-AB80,"") -> 0 | W80: =IFERROR(S80/K80,"") | X80: =S80/D80 -> 0 | Y80: =Brokerage(F80, L80, G80) -> ERR | Z80: =IF(H80=0,0,CAPITAL!$H$5*Y80) -> 0 | AA80: =IF(I80=0,0,CAPITAL!$H$6*Y80) -> 0 | AB80: =IF(J80=0,0,CAPITAL!$H$7*Y80) -> 0
A81: SILVERBEES | B81: 73 | C81: =ENTRY!B75 -> SILVERBEES | D81: =CAPITAL!$C$2 -> 3350000 | E81: =ENTRY!C75 | F81: =ENTRY!D75 | G81: =ENTRY!E75 | H81: =G81*ENTRY!$O75 -> 0 | I81: =G81*ENTRY!$P75 -> 0 | J81: =G81*ENTRY!$Q75 -> 0 | K81: =F81*G81 -> 0 | L81: =ENTRY!F75 | M81: =ENTRY!G75 | N81: =IFERROR(((L81-F81)*G81)/K81,"") | O81: =IFERROR(N81*K81,"") -> 0 | P81: =IFERROR((F81*H81)*N81,"") -> 0 | Q81: =IFERROR((F81*I81)*N81,"") -> 0 | R81: =IFERROR((F81*J81)*N81,"") -> 0 | S81: =IFERROR(O81-Y81,"") | T81: =IFERROR(P81-Z81,"") -> 0 | U81: =IFERROR(Q81-AA81,"") -> 0 | V81: =IFERROR(R81-AB81,"") -> 0 | W81: =IFERROR(S81/K81,"") | X81: =IFERROR(S81/D81,"") -> 0 | Y81: =Brokerage(F81, L81, G81) -> ERR | Z81: =IF(H81=0,0,CAPITAL!$H$5*Y81) -> 0 | AA81: =IF(I81=0,0,CAPITAL!$H$6*Y81) -> 0 | AB81: =IF(J81=0,0,CAPITAL!$H$7*Y81) -> 0
A82: HDFCSML250 | B82: 74 | C82: =ENTRY!B76 -> SILVERBEES | D82: =CAPITAL!$C$2 -> 3350000 | E82: =ENTRY!C76 | F82: =ENTRY!D76 | G82: =ENTRY!E76 | H82: =G82*ENTRY!$O76 -> 0 | I82: =G82*ENTRY!$P76 -> 0 | J82: =G82*ENTRY!$Q76 -> 0 | K82: =F82*G82 -> 0 | L82: =ENTRY!F76 | M82: =ENTRY!G76 | N82: =IFERROR(((L82-F82)*G82)/K82,"") | O82: =IFERROR(N82*K82,"") -> 0 | P82: =IFERROR((F82*H82)*N82,"") -> 0 | Q82: =IFERROR((F82*I82)*N82,"") -> 0 | R82: =IFERROR((F82*J82)*N82,"") -> 0 | S82: =IFERROR(O82-Y82,"") | T82: =IFERROR(P82-Z82,"") -> 0 | U82: =IFERROR(Q82-AA82,"") -> 0 | V82: =IFERROR(R82-AB82,"") -> 0 | W82: =IFERROR(S82/K82,"") | X82: =S82/D82 -> 0 | Y82: =Brokerage(F82, L82, G82) -> ERR | Z82: =IF(H82=0,0,CAPITAL!$H$5*Y82) -> 0 | AA82: =IF(I82=0,0,CAPITAL!$H$6*Y82) -> 0 | AB82: =IF(J82=0,0,CAPITAL!$H$7*Y82) -> 0
A83: PSUBNKBEES | B83: 75 | C83: =ENTRY!B77 -> SILVERBEES | D83: =CAPITAL!$C$2 -> 3350000 | E83: =ENTRY!C77 | F83: =ENTRY!D77 | G83: =ENTRY!E77 | H83: =G83*ENTRY!$O77 -> 0 | I83: =G83*ENTRY!$P77 -> 0 | J83: =G83*ENTRY!$Q77 -> 0 | K83: =F83*G83 -> 0 | L83: =ENTRY!F77 | M83: =ENTRY!G77 | N83: =IFERROR(((L83-F83)*G83)/K83,"") | O83: =IFERROR(N83*K83,"") -> 0 | P83: =IFERROR((F83*H83)*N83,"") -> 0 | Q83: =IFERROR((F83*I83)*N83,"") -> 0 | R83: =IFERROR((F83*J83)*N83,"") -> 0 | S83: =IFERROR(O83-Y83,"") | T83: =IFERROR(P83-Z83,"") -> 0 | U83: =IFERROR(Q83-AA83,"") -> 0 | V83: =IFERROR(R83-AB83,"") -> 0 | W83: =IFERROR(S83/K83,"") | X83: =IFERROR(S83/D83,"") -> 0 | Y83: =Brokerage(F83, L83, G83) -> ERR | Z83: =IF(H83=0,0,CAPITAL!$H$5*Y83) -> 0 | AA83: =IF(I83=0,0,CAPITAL!$H$6*Y83) -> 0 | AB83: =IF(J83=0,0,CAPITAL!$H$7*Y83) -> 0
A84: INFRABEES | B84: 76 | C84: =ENTRY!B78 -> SILVERBEES | D84: =CAPITAL!$C$2 -> 3350000 | E84: =ENTRY!C78 | F84: =ENTRY!D78 | G84: =ENTRY!E78 | H84: =G84*ENTRY!$O78 -> 0 | I84: =G84*ENTRY!$P78 -> 0 | J84: =G84*ENTRY!$Q78 -> 0 | K84: =F84*G84 -> 0 | L84: =ENTRY!F78 | M84: =ENTRY!G78 | N84: =IFERROR(((L84-F84)*G84)/K84,"") | O84: =IFERROR(N84*K84,"") -> 0 | P84: =IFERROR((F84*H84)*N84,"") -> 0 | Q84: =IFERROR((F84*I84)*N84,"") -> 0 | R84: =IFERROR((F84*J84)*N84,"") -> 0 | S84: =IFERROR(O84-Y84,"") | T84: =IFERROR(P84-Z84,"") -> 0 | U84: =IFERROR(Q84-AA84,"") -> 0 | V84: =IFERROR(R84-AB84,"") -> 0 | W84: =IFERROR(S84/K84,"") | X84: =S84/D84 -> 0 | Y84: =Brokerage(F84, L84, G84) -> ERR | Z84: =IF(H84=0,0,CAPITAL!$H$5*Y84) -> 0 | AA84: =IF(I84=0,0,CAPITAL!$H$6*Y84) -> 0 | AB84: =IF(J84=0,0,CAPITAL!$H$7*Y84) -> 0
A85: MID150BEES | B85: 77 | C85: =ENTRY!B79 -> SILVERBEES | D85: =CAPITAL!$C$2 -> 3350000 | E85: =ENTRY!C79 | F85: =ENTRY!D79 | G85: =ENTRY!E79 | H85: =G85*ENTRY!$O79 -> 0 | I85: =G85*ENTRY!$P79 -> 0 | J85: =G85*ENTRY!$Q79 -> 0 | K85: =F85*G85 -> 0 | L85: =ENTRY!F79 | M85: =ENTRY!G79 | N85: =IFERROR(((L85-F85)*G85)/K85,"") | O85: =IFERROR(N85*K85,"") -> 0 | P85: =IFERROR((F85*H85)*N85,"") -> 0 | Q85: =IFERROR((F85*I85)*N85,"") -> 0 | R85: =IFERROR((F85*J85)*N85,"") -> 0 | S85: =IFERROR(O85-Y85,"") | T85: =IFERROR(P85-Z85,"") -> 0 | U85: =IFERROR(Q85-AA85,"") -> 0 | V85: =IFERROR(R85-AB85,"") -> 0 | W85: =IFERROR(S85/K85,"") | X85: =IFERROR(S85/D85,"") -> 0 | Y85: =Brokerage(F85, L85, G85) -> ERR | Z85: =IF(H85=0,0,CAPITAL!$H$5*Y85) -> 0 | AA85: =IF(I85=0,0,CAPITAL!$H$6*Y85) -> 0 | AB85: =IF(J85=0,0,CAPITAL!$H$7*Y85) -> 0
A86: EVINDIA | B86: 79 | C86: =ENTRY!B80 -> SILVERBEES | D86: =CAPITAL!$C$2 -> 3350000 | E86: =ENTRY!C80 | F86: =ENTRY!D80 | G86: =ENTRY!E80 | H86: =G86*ENTRY!$O80 -> 0 | I86: =G86*ENTRY!$P80 -> 0 | J86: =G86*ENTRY!$Q80 -> 0 | K86: =F86*G86 -> 0 | L86: =ENTRY!F80 | M86: =ENTRY!G80 | N86: =IFERROR(((L86-F86)*G86)/K86,"") | O86: =IFERROR(N86*K86,"") -> 0 | P86: =IFERROR((F86*H86)*N86,"") -> 0 | Q86: =IFERROR((F86*I86)*N86,"") -> 0 | R86: =IFERROR((F86*J86)*N86,"") -> 0 | S86: =IFERROR(O86-Y86,"") | T86: =IFERROR(P86-Z86,"") -> 0 | U86: =IFERROR(Q86-AA86,"") -> 0 | V86: =IFERROR(R86-AB86,"") -> 0 | W86: =IFERROR(S86/K86,"") | X86: =S86/D86 -> 0 | Y86: =Brokerage(F86, L86, G86) -> ERR | Z86: =IF(H86=0,0,CAPITAL!$H$5*Y86) -> 0 | AA86: =IF(I86=0,0,CAPITAL!$H$6*Y86) -> 0 | AB86: =IF(J86=0,0,CAPITAL!$H$7*Y86) -> 0
A87: EVINDIA | B87: 80 | C87: =ENTRY!B81 -> SILVERBEES | D87: =CAPITAL!$C$2 -> 3350000 | E87: =ENTRY!C81 | F87: =ENTRY!D81 | G87: =ENTRY!E81 | H87: =G87*ENTRY!$O81 -> 0 | I87: =G87*ENTRY!$P81 -> 0 | J87: =G87*ENTRY!$Q81 -> 0 | K87: =F87*G87 -> 0 | L87: =ENTRY!F81 | M87: =ENTRY!G81 | N87: =IFERROR(((L87-F87)*G87)/K87,"") | O87: =IFERROR(N87*K87,"") -> 0 | P87: =IFERROR((F87*H87)*N87,"") -> 0 | Q87: =IFERROR((F87*I87)*N87,"") -> 0 | R87: =IFERROR((F87*J87)*N87,"") -> 0 | S87: =IFERROR(O87-Y87,"") | T87: =IFERROR(P87-Z87,"") -> 0 | U87: =IFERROR(Q87-AA87,"") -> 0 | V87: =IFERROR(R87-AB87,"") -> 0 | W87: =IFERROR(S87/K87,"") | X87: =IFERROR(S87/D87,"") -> 0 | Y87: =Brokerage(F87, L87, G87) -> ERR | Z87: =IF(H87=0,0,CAPITAL!$H$5*Y87) -> 0 | AA87: =IF(I87=0,0,CAPITAL!$H$6*Y87) -> 0 | AB87: =IF(J87=0,0,CAPITAL!$H$7*Y87) -> 0
A88: GOLD360 | B88: 82 | C88: =ENTRY!B82 -> SILVERBEES | D88: =CAPITAL!$C$2 -> 3350000 | E88: =ENTRY!C82 | F88: =ENTRY!D82 | G88: =ENTRY!E82 | H88: =G88*ENTRY!$O82 -> 0 | I88: =G88*ENTRY!$P82 -> 0 | J88: =G88*ENTRY!$Q82 -> 0 | K88: =F88*G88 -> 0 | L88: =ENTRY!F82 | M88: =ENTRY!G82 | N88: =IFERROR(((L88-F88)*G88)/K88,"") | O88: =IFERROR(N88*K88,"") -> 0 | P88: =IFERROR((F88*H88)*N88,"") -> 0 | Q88: =IFERROR((F88*I88)*N88,"") -> 0 | R88: =IFERROR((F88*J88)*N88,"") -> 0 | S88: =IFERROR(O88-Y88,"") | T88: =IFERROR(P88-Z88,"") -> 0 | U88: =IFERROR(Q88-AA88,"") -> 0 | V88: =IFERROR(R88-AB88,"") -> 0 | W88: =IFERROR(S88/K88,"") | X88: =S88/D88 -> 0 | Y88: =Brokerage(F88, L88, G88) -> ERR | Z88: =IF(H88=0,0,CAPITAL!$H$5*Y88) -> 0 | AA88: =IF(I88=0,0,CAPITAL!$H$6*Y88) -> 0 | AB88: =IF(J88=0,0,CAPITAL!$H$7*Y88) -> 0
B89: 83 | C89: =ENTRY!B83 -> SILVERBEES | D89: =CAPITAL!$C$2 -> 3350000 | E89: =ENTRY!C83 | F89: =ENTRY!D83 | G89: =ENTRY!E83 | H89: =G89*ENTRY!$O83 -> 0 | I89: =G89*ENTRY!$P83 -> 0 | J89: =G89*ENTRY!$Q83 -> 0 | K89: =F89*G89 -> 0 | L89: =ENTRY!F83 | M89: =ENTRY!G83 | N89: =IFERROR(((L89-F89)*G89)/K89,"") | O89: =IFERROR(N89*K89,"") -> 0 | P89: =IFERROR((F89*H89)*N89,"") -> 0 | Q89: =IFERROR((F89*I89)*N89,"") -> 0 | R89: =IFERROR((F89*J89)*N89,"") -> 0 | S89: =IFERROR(O89-Y89,"") | T89: =IFERROR(P89-Z89,"") -> 0 | U89: =IFERROR(Q89-AA89,"") -> 0 | V89: =IFERROR(R89-AB89,"") -> 0 | W89: =IFERROR(S89/K89,"") | X89: =IFERROR(S89/D89,"") -> 0 | Y89: =Brokerage(F89, L89, G89) -> ERR | Z89: =IF(H89=0,0,CAPITAL!$H$5*Y89) -> 0 | AA89: =IF(I89=0,0,CAPITAL!$H$6*Y89) -> 0 | AB89: =IF(J89=0,0,CAPITAL!$H$7*Y89) -> 0
B90: 84 | C90: =ENTRY!B84 -> SILVERBEES | D90: =CAPITAL!$C$2 -> 3350000 | E90: =ENTRY!C84 | F90: =ENTRY!D84 | G90: =ENTRY!E84 | H90: =G90*ENTRY!$O84 -> 0 | I90: =G90*ENTRY!$P84 -> 0 | J90: =G90*ENTRY!$Q84 -> 0 | K90: =F90*G90 -> 0 | L90: =ENTRY!F84 | M90: =ENTRY!G84 | N90: =IFERROR(((L90-F90)*G90)/K90,"") | O90: =IFERROR(N90*K90,"") -> 0 | P90: =IFERROR((F90*H90)*N90,"") -> 0 | Q90: =IFERROR((F90*I90)*N90,"") -> 0 | R90: =IFERROR((F90*J90)*N90,"") -> 0 | S90: =IFERROR(O90-Y90,"") | T90: =IFERROR(P90-Z90,"") -> 0 | U90: =IFERROR(Q90-AA90,"") -> 0 | V90: =IFERROR(R90-AB90,"") -> 0 | W90: =IFERROR(S90/K90,"") | X90: =S90/D90 -> 0 | Y90: =Brokerage(F90, L90, G90) -> ERR | Z90: =IF(H90=0,0,CAPITAL!$H$5*Y90) -> 0 | AA90: =IF(I90=0,0,CAPITAL!$H$6*Y90) -> 0 | AB90: =IF(J90=0,0,CAPITAL!$H$7*Y90) -> 0
B91: 85 | C91: =ENTRY!B85 -> SILVERBEES | D91: =CAPITAL!$C$2 -> 3350000 | E91: =ENTRY!C85 | F91: =ENTRY!D85 | G91: =ENTRY!E85 | H91: =G91*ENTRY!$O85 -> 0 | I91: =G91*ENTRY!$P85 -> 0 | J91: =G91*ENTRY!$Q85 -> 0 | K91: =F91*G91 -> 0 | L91: =ENTRY!F85 | M91: =ENTRY!G85 | N91: =IFERROR(((L91-F91)*G91)/K91,"") | O91: =IFERROR(N91*K91,"") -> 0 | P91: =IFERROR((F91*H91)*N91,"") -> 0 | Q91: =IFERROR((F91*I91)*N91,"") -> 0 | R91: =IFERROR((F91*J91)*N91,"") -> 0 | S91: =IFERROR(O91-Y91,"") | T91: =IFERROR(P91-Z91,"") -> 0 | U91: =IFERROR(Q91-AA91,"") -> 0 | V91: =IFERROR(R91-AB91,"") -> 0 | W91: =IFERROR(S91/K91,"") | X91: =IFERROR(S91/D91,"") -> 0 | Y91: =Brokerage(F91, L91, G91) -> ERR | Z91: =IF(H91=0,0,CAPITAL!$H$5*Y91) -> 0 | AA91: =IF(I91=0,0,CAPITAL!$H$6*Y91) -> 0 | AB91: =IF(J91=0,0,CAPITAL!$H$7*Y91) -> 0
B92: 86 | C92: =ENTRY!B86 -> SILVERBEES | D92: =CAPITAL!$C$2 -> 3350000 | E92: =ENTRY!C86 | F92: =ENTRY!D86 | G92: =ENTRY!E86 | H92: =G92*ENTRY!$O86 -> 0 | I92: =G92*ENTRY!$P86 -> 0 | J92: =G92*ENTRY!$Q86 -> 0 | K92: =F92*G92 -> 0 | L92: =ENTRY!F86 | M92: =ENTRY!G86 | N92: =IFERROR(((L92-F92)*G92)/K92,"") | O92: =IFERROR(N92*K92,"") -> 0 | P92: =IFERROR((F92*H92)*N92,"") -> 0 | Q92: =IFERROR((F92*I92)*N92,"") -> 0 | R92: =IFERROR((F92*J92)*N92,"") -> 0 | S92: =IFERROR(O92-Y92,"") | T92: =IFERROR(P92-Z92,"") -> 0 | U92: =IFERROR(Q92-AA92,"") -> 0 | V92: =IFERROR(R92-AB92,"") -> 0 | W92: =IFERROR(S92/K92,"") | X92: =S92/D92 -> 0 | Y92: =Brokerage(F92, L92, G92) -> ERR | Z92: =IF(H92=0,0,CAPITAL!$H$5*Y92) -> 0 | AA92: =IF(I92=0,0,CAPITAL!$H$6*Y92) -> 0 | AB92: =IF(J92=0,0,CAPITAL!$H$7*Y92) -> 0
B93: 88 | C93: =ENTRY!B87 -> SILVERBEES | D93: =CAPITAL!$C$2 -> 3350000 | E93: =ENTRY!C87 | F93: =ENTRY!D87 | G93: =ENTRY!E87 | H93: =G93*ENTRY!$O87 -> 0 | I93: =G93*ENTRY!$P87 -> 0 | J93: =G93*ENTRY!$Q87 -> 0 | K93: =F93*G93 -> 0 | L93: =ENTRY!F87 | M93: =ENTRY!G87 | N93: =IFERROR(((L93-F93)*G93)/K93,"") | O93: =IFERROR(N93*K93,"") -> 0 | P93: =IFERROR((F93*H93)*N93,"") -> 0 | Q93: =IFERROR((F93*I93)*N93,"") -> 0 | R93: =IFERROR((F93*J93)*N93,"") -> 0 | S93: =IFERROR(O93-Y93,"") | T93: =IFERROR(P93-Z93,"") -> 0 | U93: =IFERROR(Q93-AA93,"") -> 0 | V93: =IFERROR(R93-AB93,"") -> 0 | W93: =IFERROR(S93/K93,"") | X93: =IFERROR(S93/D93,"") -> 0 | Y93: =Brokerage(F93, L93, G93) -> ERR | Z93: =IF(H93=0,0,CAPITAL!$H$5*Y93) -> 0 | AA93: =IF(I93=0,0,CAPITAL!$H$6*Y93) -> 0 | AB93: =IF(J93=0,0,CAPITAL!$H$7*Y93) -> 0
B94: 89 | C94: =ENTRY!B88 -> SILVERBEES | D94: =CAPITAL!$C$2 -> 3350000 | E94: =ENTRY!C88 | F94: =ENTRY!D88 | G94: =ENTRY!E88 | H94: =G94*ENTRY!$O88 -> 0 | I94: =G94*ENTRY!$P88 -> 0 | J94: =G94*ENTRY!$Q88 -> 0 | K94: =F94*G94 -> 0 | L94: =ENTRY!F88 | M94: =ENTRY!G88 | N94: =IFERROR(((L94-F94)*G94)/K94,"") | O94: =IFERROR(N94*K94,"") -> 0 | P94: =IFERROR((F94*H94)*N94,"") -> 0 | Q94: =IFERROR((F94*I94)*N94,"") -> 0 | R94: =IFERROR((F94*J94)*N94,"") -> 0 | S94: =IFERROR(O94-Y94,"") | T94: =IFERROR(P94-Z94,"") -> 0 | U94: =IFERROR(Q94-AA94,"") -> 0 | V94: =IFERROR(R94-AB94,"") -> 0 | W94: =IFERROR(S94/K94,"") | X94: =S94/D94 -> 0 | Y94: =Brokerage(F94, L94, G94) -> ERR | Z94: =IF(H94=0,0,CAPITAL!$H$5*Y94) -> 0 | AA94: =IF(I94=0,0,CAPITAL!$H$6*Y94) -> 0 | AB94: =IF(J94=0,0,CAPITAL!$H$7*Y94) -> 0
B95: 90 | C95: =ENTRY!B89 -> SILVERBEES | D95: =CAPITAL!$C$2 -> 3350000 | E95: =ENTRY!C89 | F95: =ENTRY!D89 | G95: =ENTRY!E89 | H95: =G95*ENTRY!$O89 -> 0 | I95: =G95*ENTRY!$P89 -> 0 | J95: =G95*ENTRY!$Q89 -> 0 | K95: =F95*G95 -> 0 | L95: =ENTRY!F89 | M95: =ENTRY!G89 | N95: =IFERROR(((L95-F95)*G95)/K95,"") | O95: =IFERROR(N95*K95,"") -> 0 | P95: =IFERROR((F95*H95)*N95,"") -> 0 | Q95: =IFERROR((F95*I95)*N95,"") -> 0 | R95: =IFERROR((F95*J95)*N95,"") -> 0 | S95: =IFERROR(O95-Y95,"") | T95: =IFERROR(P95-Z95,"") -> 0 | U95: =IFERROR(Q95-AA95,"") -> 0 | V95: =IFERROR(R95-AB95,"") -> 0 | W95: =IFERROR(S95/K95,"") | X95: =IFERROR(S95/D95,"") -> 0 | Y95: =Brokerage(F95, L95, G95) -> ERR | Z95: =IF(H95=0,0,CAPITAL!$H$5*Y95) -> 0 | AA95: =IF(I95=0,0,CAPITAL!$H$6*Y95) -> 0 | AB95: =IF(J95=0,0,CAPITAL!$H$7*Y95) -> 0
B96: 91 | C96: =ENTRY!B90 -> SILVERBEES | D96: =CAPITAL!$C$2 -> 3350000 | E96: =ENTRY!C90 | F96: =ENTRY!D90 | G96: =ENTRY!E90 | H96: =G96*ENTRY!$O90 -> 0 | I96: =G96*ENTRY!$P90 -> 0 | J96: =G96*ENTRY!$Q90 -> 0 | K96: =F96*G96 -> 0 | L96: =ENTRY!F90 | M96: =ENTRY!G90 | N96: =IFERROR(((L96-F96)*G96)/K96,"") | O96: =IFERROR(N96*K96,"") -> 0 | P96: =IFERROR((F96*H96)*N96,"") -> 0 | Q96: =IFERROR((F96*I96)*N96,"") -> 0 | R96: =IFERROR((F96*J96)*N96,"") -> 0 | S96: =IFERROR(O96-Y96,"") | T96: =IFERROR(P96-Z96,"") -> 0 | U96: =IFERROR(Q96-AA96,"") -> 0 | V96: =IFERROR(R96-AB96,"") -> 0 | W96: =IFERROR(S96/K96,"") | X96: =S96/D96 -> 0 | Y96: =Brokerage(F96, L96, G96) -> ERR | Z96: =IF(H96=0,0,CAPITAL!$H$5*Y96) -> 0 | AA96: =IF(I96=0,0,CAPITAL!$H$6*Y96) -> 0 | AB96: =IF(J96=0,0,CAPITAL!$H$7*Y96) -> 0
B97: 92 | C97: =ENTRY!B91 -> SILVERBEES | D97: =CAPITAL!$C$2 -> 3350000 | E97: =ENTRY!C91 | F97: =ENTRY!D91 | G97: =ENTRY!E91 | H97: =G97*ENTRY!$O91 -> 0 | I97: =G97*ENTRY!$P91 -> 0 | J97: =G97*ENTRY!$Q91 -> 0 | K97: =F97*G97 -> 0 | L97: =ENTRY!F91 | M97: =ENTRY!G91 | N97: =IFERROR(((L97-F97)*G97)/K97,"") | O97: =IFERROR(N97*K97,"") -> 0 | P97: =IFERROR((F97*H97)*N97,"") -> 0 | Q97: =IFERROR((F97*I97)*N97,"") -> 0 | R97: =IFERROR((F97*J97)*N97,"") -> 0 | S97: =IFERROR(O97-Y97,"") | T97: =IFERROR(P97-Z97,"") -> 0 | U97: =IFERROR(Q97-AA97,"") -> 0 | V97: =IFERROR(R97-AB97,"") -> 0 | W97: =IFERROR(S97/K97,"") | X97: =IFERROR(S97/D97,"") -> 0 | Y97: =Brokerage(F97, L97, G97) -> ERR | Z97: =IF(H97=0,0,CAPITAL!$H$5*Y97) -> 0 | AA97: =IF(I97=0,0,CAPITAL!$H$6*Y97) -> 0 | AB97: =IF(J97=0,0,CAPITAL!$H$7*Y97) -> 0
B98: 93 | C98: =ENTRY!B92 -> SILVERBEES | D98: =CAPITAL!$C$2 -> 3350000 | E98: =ENTRY!C92 | F98: =ENTRY!D92 | G98: =ENTRY!E92 | H98: =G98*ENTRY!$O92 -> 0 | I98: =G98*ENTRY!$P92 -> 0 | J98: =G98*ENTRY!$Q92 -> 0 | K98: =F98*G98 -> 0 | L98: =ENTRY!F92 | M98: =ENTRY!G92 | N98: =IFERROR(((L98-F98)*G98)/K98,"") | O98: =IFERROR(N98*K98,"") -> 0 | P98: =IFERROR((F98*H98)*N98,"") -> 0 | Q98: =IFERROR((F98*I98)*N98,"") -> 0 | R98: =IFERROR((F98*J98)*N98,"") -> 0 | S98: =IFERROR(O98-Y98,"") | T98: =IFERROR(P98-Z98,"") -> 0 | U98: =IFERROR(Q98-AA98,"") -> 0 | V98: =IFERROR(R98-AB98,"") -> 0 | W98: =IFERROR(S98/K98,"") | X98: =S98/D98 -> 0 | Y98: =Brokerage(F98, L98, G98) -> ERR | Z98: =IF(H98=0,0,CAPITAL!$H$5*Y98) -> 0 | AA98: =IF(I98=0,0,CAPITAL!$H$6*Y98) -> 0 | AB98: =IF(J98=0,0,CAPITAL!$H$7*Y98) -> 0
B99: 94 | C99: =ENTRY!B93 -> SILVERBEES | D99: =CAPITAL!$C$2 -> 3350000 | E99: =ENTRY!C93 | F99: =ENTRY!D93 | G99: =ENTRY!E93 | H99: =G99*ENTRY!$O93 -> 0 | I99: =G99*ENTRY!$P93 -> 0 | J99: =G99*ENTRY!$Q93 -> 0 | K99: =F99*G99 -> 0 | L99: =ENTRY!F93 | M99: =ENTRY!G93 | N99: =IFERROR(((L99-F99)*G99)/K99,"") | O99: =IFERROR(N99*K99,"") -> 0 | P99: =IFERROR((F99*H99)*N99,"") -> 0 | Q99: =IFERROR((F99*I99)*N99,"") -> 0 | R99: =IFERROR((F99*J99)*N99,"") -> 0 | S99: =IFERROR(O99-Y99,"") | T99: =IFERROR(P99-Z99,"") -> 0 | U99: =IFERROR(Q99-AA99,"") -> 0 | V99: =IFERROR(R99-AB99,"") -> 0 | W99: =IFERROR(S99/K99,"") | X99: =IFERROR(S99/D99,"") -> 0 | Y99: =Brokerage(F99, L99, G99) -> ERR | Z99: =IF(H99=0,0,CAPITAL!$H$5*Y99) -> 0 | AA99: =IF(I99=0,0,CAPITAL!$H$6*Y99) -> 0 | AB99: =IF(J99=0,0,CAPITAL!$H$7*Y99) -> 0
B100: 95 | C100: =ENTRY!B94 -> SILVERBEES | D100: =CAPITAL!$C$2 -> 3350000 | E100: =ENTRY!C94 | F100: =ENTRY!D94 | G100: =ENTRY!E94 | H100: =G100*ENTRY!$O94 -> 0 | I100: =G100*ENTRY!$P94 -> 0 | J100: =G100*ENTRY!$Q94 -> 0 | K100: =F100*G100 -> 0 | L100: =ENTRY!F94 | M100: =ENTRY!G94 | N100: =IFERROR(((L100-F100)*G100)/K100,"") | O100: =IFERROR(N100*K100,"") -> 0 | P100: =IFERROR((F100*H100)*N100,"") -> 0 | Q100: =IFERROR((F100*I100)*N100,"") -> 0 | R100: =IFERROR((F100*J100)*N100,"") -> 0 | S100: =IFERROR(O100-Y100,"") | T100: =IFERROR(P100-Z100,"") -> 0 | U100: =IFERROR(Q100-AA100,"") -> 0 | V100: =IFERROR(R100-AB100,"") -> 0 | W100: =IFERROR(S100/K100,"") | X100: =S100/D100 -> 0 | Y100: =Brokerage(F100, L100, G100) -> ERR | Z100: =IF(H100=0,0,CAPITAL!$H$5*Y100) -> 0 | AA100: =IF(I100=0,0,CAPITAL!$H$6*Y100) -> 0 | AB100: =IF(J100=0,0,CAPITAL!$H$7*Y100) -> 0
B101: 96 | C101: =ENTRY!B95 -> SILVERBEES | D101: =CAPITAL!$C$2 -> 3350000 | E101: =ENTRY!C95 | F101: =ENTRY!D95 | G101: =ENTRY!E95 | H101: =G101*ENTRY!$O95 -> 0 | I101: =G101*ENTRY!$P95 -> 0 | J101: =G101*ENTRY!$Q95 -> 0 | K101: =F101*G101 -> 0 | L101: =ENTRY!F95 | M101: =ENTRY!G95 | N101: =IFERROR(((L101-F101)*G101)/K101,"") | O101: =IFERROR(N101*K101,"") -> 0 | P101: =IFERROR((F101*H101)*N101,"") -> 0 | Q101: =IFERROR((F101*I101)*N101,"") -> 0 | R101: =IFERROR((F101*J101)*N101,"") -> 0 | S101: =IFERROR(O101-Y101,"") | T101: =IFERROR(P101-Z101,"") -> 0 | U101: =IFERROR(Q101-AA101,"") -> 0 | V101: =IFERROR(R101-AB101,"") -> 0 | W101: =IFERROR(S101/K101,"") | X101: =IFERROR(S101/D101,"") -> 0 | Y101: =Brokerage(F101, L101, G101) -> ERR | Z101: =IF(H101=0,0,CAPITAL!$H$5*Y101) -> 0 | AA101: =IF(I101=0,0,CAPITAL!$H$6*Y101) -> 0 | AB101: =IF(J101=0,0,CAPITAL!$H$7*Y101) -> 0
B102: 97 | C102: =ENTRY!B96 -> SILVERBEES | D102: =CAPITAL!$C$2 -> 3350000 | E102: =ENTRY!C96 | F102: =ENTRY!D96 | G102: =ENTRY!E96 | H102: =G102*ENTRY!$O96 -> 0 | I102: =G102*ENTRY!$P96 -> 0 | J102: =G102*ENTRY!$Q96 -> 0 | K102: =F102*G102 -> 0 | L102: =ENTRY!F96 | M102: =ENTRY!G96 | N102: =IFERROR(((L102-F102)*G102)/K102,"") | O102: =IFERROR(N102*K102,"") -> 0 | P102: =IFERROR((F102*H102)*N102,"") -> 0 | Q102: =IFERROR((F102*I102)*N102,"") -> 0 | R102: =IFERROR((F102*J102)*N102,"") -> 0 | S102: =IFERROR(O102-Y102,"") | T102: =IFERROR(P102-Z102,"") -> 0 | U102: =IFERROR(Q102-AA102,"") -> 0 | V102: =IFERROR(R102-AB102,"") -> 0 | W102: =IFERROR(S102/K102,"") | X102: =S102/D102 -> 0 | Y102: =Brokerage(F102, L102, G102) -> ERR | Z102: =IF(H102=0,0,CAPITAL!$H$5*Y102) -> 0 | AA102: =IF(I102=0,0,CAPITAL!$H$6*Y102) -> 0 | AB102: =IF(J102=0,0,CAPITAL!$H$7*Y102) -> 0
...

Sheet SA_PROFIT_SHARING
A2: Total Gain on GIVEN Capital → | E2: =IFERROR(__xludf.DUMMYFUNCTION("SUM( FILTER(JOURNAL!X9:X1015, ISNUMBER(JOURNAL!X9:X1015)) )"),0.015051871641791037) -> 0.015051872 | F2: =JOURNAL!T6 -> 633.45943
A4: Availabe for Withdraw | D4: =F2-(SUM(D9:D62)) -> 628.45943 | E4: =SUM(E9:E62) -> 4.5 | F4: =SUM(F9:F62) -> 0.5
A6: NO. | B6: CAPITAL | C6: DATE | D6: AMOUNT | E6: SUJAY | F6: DENISH | G6: SHARING STATUS
E7: 0.9 | F7: 0.1
A9: 1 | B9: =CAPITAL!$C$5 -> 150000 | C9: 45986 | D9: 5 | E9: =D9*$E$7 -> 4.5 | F9: =D9*$F$7 -> 0.5 | G9: DONE
A10: 2 | B10: =CAPITAL!$C$5 -> 150000 | E10: =D10*$E$7 -> 0 | F10: =D10*$F$7 -> 0
A11: 3 | B11: =CAPITAL!$C$5 -> 150000 | E11: =D11*$E$7 -> 0 | F11: =D11*$F$7 -> 0
A12: 4 | B12: =CAPITAL!$C$5 -> 150000 | E12: =D12*$E$7 -> 0 | F12: =D12*$F$7 -> 0
A13: 5 | B13: =CAPITAL!$C$5 -> 150000 | E13: =D13*$E$7 -> 0 | F13: =D13*$F$7 -> 0
A14: 6 | B14: =CAPITAL!$C$5 -> 150000 | E14: =D14*$E$7 -> 0 | F14: =D14*$F$7 -> 0
A15: 7 | B15: =CAPITAL!$C$5 -> 150000 | E15: =D15*$E$7 -> 0 | F15: =D15*$F$7 -> 0
A16: 8 | B16: =CAPITAL!$C$5 -> 150000 | E16: =D16*$E$7 -> 0 | F16: =D16*$F$7 -> 0
A17: 9 | B17: =CAPITAL!$C$5 -> 150000 | E17: =D17*$E$7 -> 0 | F17: =D17*$F$7 -> 0
A18: 10 | B18: =CAPITAL!$C$5 -> 150000 | E18: =D18*$E$7 -> 0 | F18: =D18*$F$7 -> 0
A19: 11 | B19: =CAPITAL!$C$5 -> 150000 | E19: =D19*$E$7 -> 0 | F19: =D19*$F$7 -> 0
A20: 12 | B20: =CAPITAL!$C$5 -> 150000 | E20: =D20*$E$7 -> 0 | F20: =D20*$F$7 -> 0
A21: 13 | B21: =CAPITAL!$C$5 -> 150000 | E21: =D21*$E$7 -> 0 | F21: =D21*$F$7 -> 0
... A63: 55 | B63: =CAPITAL!$C$5 -> 150000 | E63: =D63*$E$7 -> 0 | F63: =D63*$F$7 -> 0

Sheet SG_PROFIT_SHARING
E1: 2025 Profit
A2: Total Gain on GIVEN Capital → | E2: =IFERROR(__xludf.DUMMYFUNCTION("SUM( FILTER(JOURNAL!X9:X1015, ISNUMBER(JOURNAL!X9:X1015)) )"),0.015051871641791037) -> 0.015051872 | F2: =JOURNAL!U6+F1 -> 2520.9252
A4: Availabe for Withdraw | D4: =F2-(SUM(D9:D62)) -> 2520.9252 | E4: =SUM(E9:E62) -> 0 | F4: =SUM(F9:F62) -> 0
A6: NO. | B6: CAPITAL | C6: DATE | D6: AMOUNT | E6: SG | F6: DENISH | G6: SHARING STATUS
E7: 0.9 | F7: 0.1
A9: 1 | B9: =CAPITAL!$C$6 -> 700000 | C9: 45986 | E9: =D9*$E$7 -> 0 | F9: =D9*$F$7 -> 0 | G9: DONE
A10: 2 | B10: =CAPITAL!$C$6 -> 700000 | E10: =D10*$E$7 -> 0 | F10: =D10*$F$7 -> 0
A11: 3 | B11: =CAPITAL!$C$6 -> 700000 | E11: =D11*$E$7 -> 0 | F11: =D11*$F$7 -> 0
A12: 4 | B12: =CAPITAL!$C$6 -> 700000 | E12: =D12*$E$7 -> 0 | F12: =D12*$F$7 -> 0
A13: 5 | B13: =CAPITAL!$C$6 -> 700000 | E13: =D13*$E$7 -> 0 | F13: =D13*$F$7 -> 0
A14: 6 | B14: =CAPITAL!$C$6 -> 700000 | E14: =D14*$E$7 -> 0 | F14: =D14*$F$7 -> 0
A15: 7 | B15: =CAPITAL!$C$6 -> 700000 | E15: =D15*$E$7 -> 0 | F15: =D15*$F$7 -> 0
A16: 8 | B16: =CAPITAL!$C$6 -> 700000 | E16: =D16*$E$7 -> 0 | F16: =D16*$F$7 -> 0
A17: 9 | B17: =CAPITAL!$C$6 -> 700000 | E17: =D17*$E$7 -> 0 | F17: =D17*$F$7 -> 0
A18: 10 | B18: =CAPITAL!$C$6 -> 700000 | E18: =D18*$E$7 -> 0 | F18: =D18*$F$7 -> 0
A19: 11 | B19: =CAPITAL!$C$6 -> 700000 | E19: =D19*$E$7 -> 0 | F19: =D19*$F$7 -> 0
A20: 12 | B20: =CAPITAL!$C$6 -> 700000 | E20: =D20*$E$7 -> 0 | F20: =D20*$F$7 -> 0
A21: 13 | B21: =CAPITAL!$C$6 -> 700000 | E21: =D21*$E$7 -> 0 | F21: =D21*$F$7 -> 0
... A63: 55 | B63: =CAPITAL!$C$6 -> 700000 | E63: =D63*$E$7 -> 0 | F63: =D63*$F$7 -> 0

Sheet TXN
A1: SA - FUND GIVEN | E1: SG - FUND GIVEN
A3: NO. | B3: DATE | C3: AMOUNT | E3: NO. | F3: DATE | G3: AMOUNT
B5: SUM | C5: =SUM(C7:C56) -> 150000 | F5: SUM | G5: =SUM(G7:G56) -> 700000
A7: 1 | B7: 45782 | C7: 50000 | E7: 1 | F7: 45789 | G7: 200000
A8: 2 | B8: 45798 | C8: 40000 | E8: 2 | F8: 45834 | G8: 200000
A9: 3 | B9: 45832 | C9: 60000 | E9: 3 | F9: 45874 | G9: 100000
A10: 4 | E10: 4 | F10: 45979 | G10: 200000
A11: 5 | E11: 5
A12: 6 | E12: 6
E13: 7
E14: 8
E15: 9
E16: 10
E17: 11
E18: 12
E19: 13
E20: 14
E21: 15
E22: 16

Sheet Brokerage
B4: Before Brokrage | C4: TOTAL PROFIT | E4: BUY | F4: SELL | G4: QNT | H4: Profit | I4: Net Profit
B5: Total Brokrage | E5: =SA_JOURNAL!F9 -> #REF! | F5: =SA_JOURNAL!I9 -> #REF! | G5: =SA_JOURNAL!G9 -> #REF! | H5: =(F5-E5)*G5 -> #REF! | I5: =H5-E16 -> #REF!
D6: VALUE | E6: =E5*G5 -> #REF! | F6: =F5*G5 -> #REF! | G6: =E6+F6 -> #REF!
B8: Net Release | E8: =E6*0.001 -> #REF!
C9: STT/CTT | D9: 0.001 | E9: =E6*D9 -> #REF! | F9: =F6*D9 -> #REF! | G9: =E9+F9 -> #REF!
C10: TRANSACTION | D10: 3e-05 | E10: =D10*G6 -> #REF! | H10: 0.6
C11: SEBI | D11: 1e-06 | E11: =G6*D11 -> #REF! | H11: 0.02
D12: Transaction + SEBI | E12: =E10+E11 -> #REF!
C13: GST ON TRANSACTION AND SEBI CHARGES | D13: 0.18 | E13: =E12*D13 -> #REF! | K13: 0.0001/100
C14: STAMP DUTY (Buy Only) | D14: 0.00015 | E14: =D14*E6 -> #REF! | H14: 1.5 | K14: =0.001/100 -> 1e-05
E16: =G9+E10+E11+E13+E14 -> #REF!
